[
    {
        "Id": 1,
        "Name": "Lv.25 BC Supplies",
        "Desc": "Lv.25 BC Supplies",
        "ConsumeId": 3,
        "ConsumeCount": 30,
        "RewardId": 90001,
        "ConditionId": [
            8000
        ],
        "TimeToEffectStr": "2021/7/15 7:00",
        "BuyLimitTimes": 1,
        "BuyLimitType": 0,
        "Icon": "UiB25",
        "UiType": 6,
        "Priority": 11000,
        "LogType": 4
    },
    {
        "Id": 2,
        "Name": "Lv.25 RC Supplies",
        "Desc": "Lv.25 RC Supplies",
        "ConsumeId": 5,
        "ConsumeCount": 5,
        "RewardId": 90002,
        "ConditionId": [
            8000
        ],
        "TimeToEffectStr": "2021/7/15 7:00",
        "BuyLimitTimes": 1,
        "BuyLimitType": 0,
        "Icon": "UiG25",
        "UiType": 6,
        "Priority": 11100,
        "LogType": 3
    },
    {
        "Id": 3,
        "Name": "Lv.35 BC Supplies",
        "Desc": "Lv.35 BC Supplies",
        "ConsumeId": 3,
        "ConsumeCount": 80,
        "RewardId": 90003,
        "PrePurchaseId": 1,
        "ConditionId": [
            8001
        ],
        "TimeToEffectStr": "2021/7/15 7:00",
        "BuyLimitTimes": 1,
        "BuyLimitType": 0,
        "Icon": "UiB35",
        "UiType": 6,
        "Priority": 11200,
        "LogType": 4
    },
    {
        "Id": 4,
        "Name": "Lv.35 RC Supplies",
        "Desc": "Lv.35 RC Supplies",
        "ConsumeId": 5,
        "ConsumeCount": 28,
        "RewardId": 90004,
        "PrePurchaseId": 2,
        "ConditionId": [
            8001
        ],
        "TimeToEffectStr": "2021/7/15 7:00",
        "BuyLimitTimes": 1,
        "BuyLimitType": 0,
        "Icon": "UiG35",
        "UiType": 6,
        "Priority": 11300,
        "LogType": 3
    },
    {
        "Id": 5,
        "Name": "Lv.55 BC Supplies",
        "Desc": "Lv.55 BC Supplies",
        "ConsumeId": 3,
        "ConsumeCount": 150,
        "RewardId": 90005,
        "PrePurchaseId": 3,
        "ConditionId": [
            900000003
        ],
        "TimeToEffectStr": "2021/7/15 7:00",
        "BuyLimitTimes": 1,
        "BuyLimitType": 0,
        "Icon": "UiB55",
        "UiType": 6,
        "Priority": 11400,
        "LogType": 4
    },
    {
        "Id": 6,
        "Name": "Lv.55 RC Supplies",
        "Desc": "Lv.55 RC Supplies",
        "ConsumeId": 5,
        "ConsumeCount": 34,
        "RewardId": 90006,
        "PrePurchaseId": 4,
        "ConditionId": [
            900000003
        ],
        "TimeToEffectStr": "2021/7/15 7:00",
        "BuyLimitTimes": 1,
        "BuyLimitType": 0,
        "Icon": "UiG55",
        "UiType": 6,
        "Priority": 11500,
        "LogType": 3
    },
    {
        "Id": 7,
        "Name": "Lv.70 BC Supplies",
        "Desc": "Lv.70 BC Supplies",
        "ConsumeId": 3,
        "ConsumeCount": 250,
        "RewardId": 90007,
        "PrePurchaseId": 5,
        "ConditionId": [
            900000004
        ],
        "TimeToEffectStr": "2021/7/15 7:00",
        "BuyLimitTimes": 1,
        "BuyLimitType": 0,
        "Icon": "UiB70",
        "UiType": 6,
        "Priority": 11600,
        "LogType": 4
    },
    {
        "Id": 8,
        "Name": "Lv.70 RC Supplies",
        "Desc": "Lv.70 RC Supplies",
        "ConsumeId": 5,
        "ConsumeCount": 59,
        "RewardId": 90008,
        "PrePurchaseId": 6,
        "ConditionId": [
            900000004
        ],
        "TimeToEffectStr": "2021/7/15 7:00",
        "BuyLimitTimes": 1,
        "BuyLimitType": 0,
        "Icon": "UiG70",
        "UiType": 6,
        "Priority": 11700,
        "LogType": 3
    },
    {
        "Id": 9,
        "Name": "Construct 10x R&D Pack -10d",
        "Desc": "1 per day for 10 days",
        "ConsumeId": 5,
        "ConsumeCount": 5,
        "RewardId": 90009,
        "MailId": 90005,
        "MailCount": 10,
        "ConditionId": [],
        "TimeToEffectStr": "2021/7/15 7:00",
        "BuyLimitTimes": 1,
        "BuyLimitType": 0,
        "Icon": "Uio1rmb",
        "Tag": 2,
        "UiType": 5,
        "Priority": 10000,
        "LogType": 3
    },
    {
        "Id": 10,
        "Name": "Tiara Coating Pack",
        "Desc": "Tiara Coating Pack",
        "ConsumeId": 5,
        "ConsumeCount": 35,
        "RewardId": 90010,
        "ConditionId": [],
        "TimeToEffectStr": "2021/7/15 7:00",
        "BuyLimitTimes": 1,
        "BuyLimitType": 0,
        "Icon": "UioLifu",
        "Tag": 1,
        "UiType": 7,
        "Priority": 30000,
        "LogType": 3
    },
    {
        "Id": 11,
        "Name": "Construct 10x R&D Bundle",
        "Desc": "Construct 10x R&D Bundle",
        "ConsumeId": 5,
        "ConsumeCount": 69,
        "RewardId": 90011,
        "ConditionId": [],
        "TimeToEffectStr": "2021/7/15 7:00",
        "BuyLimitTimes": 1,
        "BuyLimitType": 0,
        "Icon": "UioCDrew",
        "Tag": 1,
        "UiType": 5,
        "Priority": 10200,
        "LogType": 3
    },
    {
        "Id": 12,
        "Name": "Weapon 10x R&D Bundle",
        "Desc": "Weapon 10x R&D Bundle",
        "ConsumeId": 5,
        "ConsumeCount": 69,
        "RewardId": 90012,
        "ConditionId": [],
        "TimeToEffectStr": "2021/7/15 7:00",
        "BuyLimitTimes": 1,
        "BuyLimitType": 0,
        "Icon": "UioWDrew",
        "Tag": 1,
        "UiType": 5,
        "Priority": 10300,
        "LogType": 3
    },
    {
        "Id": 13,
        "Name": "Value Training Pack",
        "Desc": "1 per day for 5 days",
        "ConsumeId": 5,
        "ConsumeCount": 99,
        "MailId": 90000,
        "MailCount": 5,
        "ConditionId": [],
        "TimeToEffectStr": "2019/1/1 5:00",
        "TimeToInvalidStr": "2020/1/1 9:59",
        "BuyLimitTimes": 1,
        "BuyLimitType": 0,
        "Icon": "UioNUp",
        "UiType": 5,
        "Priority": 10500,
        "LogType": 3
    },
    {
        "Id": 14,
        "Name": "Cyberpunk Decor Set",
        "Desc": "Cyberpunk Decor Set",
        "ConsumeId": 5,
        "ConsumeCount": 60,
        "RewardId": 90013,
        "ConditionId": [],
        "TimeToEffectStr": "2019/1/1 5:00",
        "TimeToInvalidStr": "2020/1/1 9:59",
        "BuyLimitTimes": 1,
        "BuyLimitType": 0,
        "Icon": "UioNF",
        "UiType": 7,
        "Priority": 30200,
        "LogType": 3
    },
    {
        "Id": 15,
        "Name": "Weekly Limited Pack",
        "Desc": "Weekly Limited Pack",
        "RewardId": 90014,
        "ConditionId": [],
        "TimeToEffectStr": "2021/7/15 7:00",
        "BuyLimitTimes": 1,
        "BuyLimitType": 1,
        "BuyLimitParam": 10001,
        "Icon": "UioWeek",
        "IsSellOutShow": 1,
        "Tag": 1,
        "UiType": 6,
        "Priority": 5000
    },
    {
        "Id": 16,
        "Name": "Monthly Target Weapon Pack",
        "Desc": "Monthly Target Weapon Pack",
        "ConsumeId": 5,
        "ConsumeCount": 119,
        "RewardId": 90015,
        "ConditionId": [],
        "TimeToEffectStr": "2021/8/3 7:00",
        "BuyLimitTimes": 1,
        "BuyLimitType": 1,
        "BuyLimitParam": 10004,
        "Icon": "UioWDMouth",
        "IsSellOutShow": 1,
        "Tag": 1,
        "UiType": 5,
        "Priority": 10700,
        "LogType": 3
    },
    {
        "Id": 17,
        "Name": "Monthly Event Construct Pack",
        "Desc": "Monthly Event Construct Pack",
        "ConsumeId": 5,
        "ConsumeCount": 99,
        "RewardId": 90016,
        "ConditionId": [],
        "TimeToEffectStr": "2021/8/3 7:00",
        "BuyLimitTimes": 1,
        "BuyLimitType": 1,
        "BuyLimitParam": 10004,
        "Icon": "UioCDMouth2",
        "IsSellOutShow": 1,
        "Tag": 1,
        "UiType": 5,
        "Priority": 10600,
        "LogType": 3
    },
    {
        "Id": 18,
        "Name": "A-Rank Construct SSR Coating Black Card",
        "Desc": "1 per day for 10 days",
        "ConsumeId": 5,
        "ConsumeCount": 68,
        "RewardId": 90017,
        "MailId": 90001,
        "MailCount": 10,
        "ConditionId": [],
        "TimeToEffectStr": "2019/1/1 5:00",
        "TimeToInvalidStr": "2020/1/1 9:59",
        "BuyLimitTimes": 1,
        "BuyLimitType": 0,
        "Icon": "UiPurchaseIconLb1",
        "IsSellOutShow": 1,
        "UiType": 7,
        "Priority": 30300,
        "LogType": 3
    },
    {
        "Id": 19,
        "Name": "Coating Blueprint Supply",
        "Desc": "Coating Blueprint Supply",
        "ConsumeId": 5,
        "ConsumeCount": 99,
        "RewardId": 90023,
        "ConditionId": [],
        "TimeToEffectStr": "2021/7/15 7:00",
        "BuyLimitTimes": 1,
        "BuyLimitType": 1,
        "BuyLimitParam": 10004,
        "Icon": "UioPifuM",
        "IsSellOutShow": 1,
        "UiType": 7,
        "Priority": 30500,
        "LogType": 3
    },
    {
        "Id": 20,
        "Name": "S-Rank Construct SSR Coating",
        "Desc": "S-Rank Construct SSR Coating",
        "ConsumeId": 5,
        "ConsumeCount": 168,
        "RewardId": 90018,
        "ConditionId": [],
        "TimeToEffectStr": "2019/1/1 5:00",
        "TimeToInvalidStr": "2020/1/1 9:59",
        "BuyLimitTimes": 1,
        "BuyLimitType": 0,
        "Icon": "UiPurchaseIconLb1",
        "IsSellOutShow": 1,
        "UiType": 7,
        "Priority": 30400,
        "LogType": 3
    },
    {
        "Id": 21,
        "Name": "Skill Pts Daily Pack",
        "Desc": "Skill Pts Daily Pack",
        "ConsumeId": 3,
        "ConsumeCount": 10,
        "RewardId": 90019,
        "ConditionId": [],
        "TimeToEffectStr": "2021/7/15 7:00",
        "BuyLimitTimes": 1,
        "BuyLimitType": 1,
        "BuyLimitParam": 10000,
        "Icon": "UioJDay",
        "IsSellOutShow": 1,
        "UiType": 6,
        "Priority": 50100,
        "LogType": 4
    },
    {
        "Id": 22,
        "Name": "Weapon Enhance Wk Card",
        "Desc": "1 per day for 7 days",
        "ConsumeId": 5,
        "ConsumeCount": 39,
        "MailId": 90003,
        "MailCount": 7,
        "ConditionId": [],
        "TimeToEffectStr": "2021/7/15 7:00",
        "ShelvesType": 1,
        "ShelvesDays": "[1,2,3,4,5]",
        "BuyLimitTimes": 1,
        "BuyLimitType": 1,
        "BuyLimitParam": 10001,
        "Icon": "UioWMaterial",
        "IsSellOutShow": 1,
        "UiType": 6,
        "Priority": 50200,
        "LogType": 3
    },
    {
        "Id": 23,
        "Name": "Memory Enhance Wk Card",
        "Desc": "1 per day for 7 days",
        "ConsumeId": 5,
        "ConsumeCount": 39,
        "MailId": 90004,
        "MailCount": 7,
        "ConditionId": [],
        "TimeToEffectStr": "2021/7/15 7:00",
        "ShelvesType": 1,
        "ShelvesDays": "[1,2,3,4,5]",
        "BuyLimitTimes": 1,
        "BuyLimitType": 1,
        "BuyLimitParam": 10001,
        "Icon": "UioCMaterial",
        "IsSellOutShow": 1,
        "UiType": 6,
        "Priority": 50300,
        "LogType": 3
    },
    {
        "Id": 24,
        "Name": "Cogs",
        "Desc": "Cogs",
        "ConsumeId": 5,
        "ConsumeCount": 30,
        "RewardId": 90020,
        "ConditionId": [],
        "TimeToEffectStr": "2019/1/1 5:00",
        "TimeToInvalidStr": "2020/1/1 9:59",
        "BuyLimitTimes": 1,
        "BuyLimitType": 0,
        "Icon": "UioMoney",
        "IsSellOutShow": 1,
        "UiType": 6,
        "Priority": 50400,
        "LogType": 3
    },
    {
        "Id": 25,
        "Name": "Blueprint Bundle",
        "Desc": "Blueprint Bundle",
        "ConsumeId": 5,
        "ConsumeCount": 30,
        "RewardId": 90021,
        "ConditionId": [],
        "TimeToEffectStr": "2021/7/15 7:00",
        "Icon": "UioSkinD",
        "IsSellOutShow": 0,
        "UiType": 7,
        "Priority": 30500,
        "LogType": 3
    },
    {
        "Id": 26,
        "Name": "Decor Coin Bundle",
        "Desc": "Decor Coin Bundle",
        "ConsumeId": 5,
        "ConsumeCount": 60,
        "RewardId": 90022,
        "ConditionId": [],
        "TimeToEffectStr": "2021/7/15 7:00",
        "Icon": "UioFCoin",
        "IsSellOutShow": 0,
        "UiType": 7,
        "Priority": 50500,
        "LogType": 3
    },
    {
        "Id": 10000,
        "Name": "Monthly Pass",
        "Desc": "Sign-in daily to get a total of <color=#ff8338>100</color> Black Cards",
        "ConsumeId": 5,
        "ConsumeCount": 30,
        "RewardId": 91000,
        "DailyRewardId": 91001,
        "DailyRewardCount": 30,
        "ConditionId": [],
        "TimeToEffectStr": "2019/1/1 5:00",
        "TimeToInvalidStr": "2020/1/1 9:59",
        "BuyLimitType": 3,
        "BuyLimitParam": 30,
        "Icon": "UiCardMonthA",
        "IsSellOutShow": 1,
        "Tag": 1,
        "UiType": 2,
        "LogType": 2
    },
    {
        "Id": 27,
        "Name": "Weekly Value Pack",
        "Desc": "Weekly Value Pack",
        "ConsumeId": 5,
        "ConsumeCount": 59,
        "RewardId": 90024,
        "ConditionId": [],
        "TimeToEffectStr": "2019/1/1 5:00",
        "TimeToInvalidStr": "2020/1/1 9:59",
        "BuyLimitTimes": 1,
        "BuyLimitType": 1,
        "BuyLimitParam": 10001,
        "Icon": "UioXingjia",
        "IsSellOutShow": 1,
        "UiType": 5,
        "Priority": 10800,
        "LogType": 3
    },
    {
        "Id": 28,
        "Name": "Construct 10x Material Pack",
        "Desc": "Construct 10x Material Pack",
        "ConsumeId": 5,
        "ConsumeCount": 88,
        "RewardId": 90025,
        "ConditionId": [],
        "TimeToEffectStr": "2019/1/1 5:00",
        "TimeToInvalidStr": "2020/1/1 9:59",
        "BuyLimitTimes": 1,
        "BuyLimitType": 0,
        "Icon": "UioShilian",
        "UiType": 5,
        "Priority": 10400,
        "LogType": 3
    },
    {
        "Id": 29,
        "Name": "Construct Research Supply Pack",
        "Desc": "Construct Research Supply Pack",
        "ConsumeId": 5,
        "ConsumeCount": 35,
        "RewardId": 90026,
        "ConditionId": [],
        "TimeToEffectStr": "2019/1/1 5:00",
        "TimeToInvalidStr": "2020/1/1 9:59",
        "BuyLimitTimes": 2,
        "BuyLimitType": 0,
        "Icon": "UioYanfa",
        "UiType": 5,
        "Priority": 10100,
        "LogType": 3
    },
    {
        "Id": 30,
        "Name": "Gray Feather Series Pick",
        "Desc": "Gray Feather Series Pick",
        "ConsumeId": 5,
        "ConsumeCount": 126,
        "RewardId": 90027,
        "ConditionId": [],
        "TimeToEffectStr": "2019/1/1 5:00",
        "TimeToInvalidStr": "2020/1/1 9:59",
        "BuyLimitTimes": 3,
        "BuyLimitType": 0,
        "Icon": "UioZhixuan",
        "UiType": 7,
        "Priority": 30100,
        "LogType": 3
    },
    {
        "Id": 31,
        "Name": "Shooting Star - Nanami: Pulse",
        "Desc": "Nanami: Pulse Coating - Shooting Star",
        "ConsumeId": 5,
        "ConsumeCount": 154,
        "RewardId": 6510305,
        "ConditionId": [],
        "TimeToEffectStr": "2019/1/1 5:00",
        "TimeToInvalidStr": "2020/1/1 9:59",
        "BuyLimitTimes": 1,
        "BuyLimitType": 0,
        "Icon": "UioPifu31",
        "Tag": 14,
        "UiType": 7,
        "Priority": 30110,
        "LogType": 3
    },
    {
        "Id": 32,
        "Name": "Gray Feathers - Nanami: Pulse",
        "Desc": "Nanami: Pulse Coating - Gray Feathers",
        "ConsumeId": 5,
        "ConsumeCount": 154,
        "RewardId": 6510304,
        "ConditionId": [],
        "TimeToEffectStr": "2019/1/1 5:00",
        "TimeToInvalidStr": "2020/1/1 9:59",
        "BuyLimitTimes": 1,
        "BuyLimitType": 0,
        "Icon": "UioPifu32",
        "Tag": 14,
        "UiType": 7,
        "Priority": 30120,
        "LogType": 3
    },
    {
        "Id": 33,
        "Name": "Gray Feathers - Karenina: Blaster",
        "Desc": "Karenina: Blaster Coating - Gray Feathers",
        "ConsumeId": 5,
        "ConsumeCount": 126,
        "RewardId": 6710104,
        "ConditionId": [],
        "TimeToEffectStr": "2019/1/1 5:00",
        "TimeToInvalidStr": "2020/1/1 9:59",
        "BuyLimitTimes": 1,
        "BuyLimitType": 0,
        "Icon": "UioPifu33",
        "Tag": 14,
        "UiType": 7,
        "Priority": 30130,
        "LogType": 3
    },
    {
        "Id": 34,
        "Name": "Gray Feathers - Lee: Thermite",
        "Desc": "Lee: Thermite Coating - Gray Feathers",
        "ConsumeId": 5,
        "ConsumeCount": 98,
        "RewardId": 6110104,
        "ConditionId": [],
        "TimeToEffectStr": "2019/1/1 5:00",
        "TimeToInvalidStr": "2020/1/1 9:59",
        "BuyLimitTimes": 1,
        "BuyLimitType": 0,
        "Icon": "UioPifu34",
        "Tag": 14,
        "UiType": 7,
        "Priority": 30140,
        "LogType": 3
    },
    {
        "Id": 35,
        "Name": "Ashen End - Lee: Random",
        "Desc": "Lee: Random Coating - Ashen End",
        "ConsumeId": 5,
        "ConsumeCount": 154,
        "RewardId": 6110305,
        "ConditionId": [],
        "TimeToEffectStr": "2019/1/1 5:00",
        "TimeToInvalidStr": "2020/1/1 9:59",
        "BuyLimitTimes": 1,
        "BuyLimitType": 0,
        "Icon": "UioPifu35",
        "Tag": 14,
        "UiType": 7,
        "Priority": 30110,
        "LogType": 3
    },
    {
        "Id": 36,
        "Name": "Gray Feathers - Lee: Random",
        "Desc": "Lee: Random Coating - Gray Feathers",
        "ConsumeId": 5,
        "ConsumeCount": 98,
        "RewardId": 6110304,
        "ConditionId": [],
        "TimeToEffectStr": "2019/1/1 5:00",
        "TimeToInvalidStr": "2020/1/1 9:59",
        "BuyLimitTimes": 1,
        "BuyLimitType": 0,
        "Icon": "UioPifu36",
        "Tag": 14,
        "UiType": 7,
        "Priority": 30120,
        "LogType": 3
    },
    {
        "Id": 37,
        "Name": "Gothic Sentinel - Lucia: Dawn",
        "Desc": "Lucia: Dawn Coating - Gothic Sentinel",
        "ConsumeId": 5,
        "ConsumeCount": 154,
        "RewardId": 6210204,
        "ConditionId": [],
        "TimeToEffectStr": "2019/1/1 5:00",
        "TimeToInvalidStr": "2020/1/1 9:59",
        "BuyLimitTimes": 1,
        "BuyLimitType": 0,
        "Icon": "UioPifu37",
        "Tag": 14,
        "UiType": 7,
        "Priority": 30130,
        "LogType": 3
    },
    {
        "Id": 38,
        "Name": "Gray Feathers - Lucia: Dawn",
        "Desc": "Lucia: Dawn Coating - Gray Feathers",
        "ConsumeId": 5,
        "ConsumeCount": 154,
        "RewardId": 6210205,
        "ConditionId": [],
        "TimeToEffectStr": "2019/1/1 5:00",
        "TimeToInvalidStr": "2020/1/1 9:59",
        "BuyLimitTimes": 1,
        "BuyLimitType": 0,
        "Icon": "UioPifu38",
        "Tag": 14,
        "UiType": 7,
        "Priority": 30140,
        "LogType": 3
    },
    {
        "Id": 39,
        "Name": "Gray Feathers - Liv: La Paix",
        "Desc": "Liv: La Paix Coating - Gray Feathers",
        "ConsumeId": 5,
        "ConsumeCount": 154,
        "RewardId": 6310305,
        "ConditionId": [],
        "TimeToEffectStr": "2019/1/1 5:00",
        "TimeToInvalidStr": "2020/1/1 9:59",
        "BuyLimitTimes": 1,
        "BuyLimitType": 0,
        "Icon": "UioPifu39",
        "Tag": 14,
        "UiType": 7,
        "Priority": 30110,
        "LogType": 3
    },
    {
        "Id": 40,
        "Name": "Demon Gear - Karenina: Ember",
        "Desc": "Karenina: Ember Coating - Demon Gear",
        "ConsumeId": 5,
        "ConsumeCount": 154,
        "RewardId": 6710305,
        "ConditionId": [],
        "TimeToEffectStr": "2019/1/1 5:00",
        "TimeToInvalidStr": "2020/1/1 9:59",
        "BuyLimitTimes": 1,
        "BuyLimitType": 0,
        "Icon": "UioPifu40",
        "Tag": 14,
        "UiType": 7,
        "Priority": 30120,
        "LogType": 3
    },
    {
        "Id": 41,
        "Name": "Gray Feathers - Karenina: Ember",
        "Desc": "Karenina: Ember Coating - Gray Feathers",
        "ConsumeId": 5,
        "ConsumeCount": 126,
        "RewardId": 6710304,
        "ConditionId": [],
        "TimeToEffectStr": "2019/1/1 5:00",
        "TimeToInvalidStr": "2020/1/1 9:59",
        "BuyLimitTimes": 1,
        "BuyLimitType": 0,
        "Icon": "UioPifu41",
        "Tag": 14,
        "UiType": 7,
        "Priority": 30130,
        "LogType": 3
    },
    {
        "Id": 42,
        "Name": "Gray Feathers - Liv: Lux",
        "Desc": "Liv: Lux Coating - Gray Feathers",
        "ConsumeId": 5,
        "ConsumeCount": 154,
        "RewardId": 6310204,
        "ConditionId": [],
        "TimeToEffectStr": "2019/1/1 5:00",
        "TimeToInvalidStr": "2020/1/1 9:59",
        "BuyLimitTimes": 1,
        "BuyLimitType": 0,
        "Icon": "UioPifu42",
        "Tag": 14,
        "UiType": 7,
        "Priority": 30140,
        "LogType": 3
    },
    {
        "Id": 46,
        "Name": "Adventurous Spirit - Brilliance",
        "Desc": "Ayla: Brilliance Coating - Adventurous Spirit",
        "ConsumeId": 5,
        "ConsumeCount": 98,
        "RewardId": 6910104,
        "ConditionId": [],
        "TimeToEffectStr": "2021/9/24 8:00",
        "TimeToInvalidStr": "2021/10/11 7:59",
        "BuyLimitTimes": 1,
        "BuyLimitType": 0,
        "Icon": "UioPifu46",
        "Tag": 14,
        "UiType": 7,
        "Priority": 20215,
        "LogType": 3
    },
    {
        "Id": 47,
        "Name": "Aster Hare - Brilliance",
        "Desc": "Ayla: Brilliance Coating - Aster Hare",
        "ConsumeId": 5,
        "ConsumeCount": 126,
        "RewardId": 6910105,
        "ConditionId": [],
        "TimeToEffectStr": "2021/9/24 8:00",
        "TimeToInvalidStr": "2021/10/11 7:59",
        "BuyLimitTimes": 1,
        "BuyLimitType": 0,
        "Icon": "UioPifu47",
        "Tag": 14,
        "UiType": 7,
        "Priority": 20216,
        "LogType": 3
    },
    {
        "Id": 48,
        "Name": "Field Training - Astral",
        "Desc": "Watanabe: Astral Coating - Field Training",
        "ConsumeId": 5,
        "ConsumeCount": 98,
        "RewardId": 6810304,
        "ConditionId": [],
        "TimeToEffectStr": "2021/9/10 8:00",
        "TimeToInvalidStr": "2021/10/11 7:59",
        "BuyLimitTimes": 1,
        "BuyLimitType": 0,
        "Icon": "UioPifu48",
        "Tag": 14,
        "UiType": 7,
        "Priority": 20217,
        "LogType": 3
    },
    {
        "Id": 49,
        "Name": "Skyline Trial - Astral",
        "Desc": "Watanabe: Astral Coating - Skyline Trial",
        "ConsumeId": 5,
        "ConsumeCount": 126,
        "RewardId": 6810305,
        "ConditionId": [],
        "TimeToEffectStr": "2021/9/10 8:00",
        "TimeToInvalidStr": "2021/10/11 7:59",
        "BuyLimitTimes": 1,
        "BuyLimitType": 0,
        "Icon": "UioPifu49",
        "Tag": 14,
        "UiType": 7,
        "Priority": 20219,
        "LogType": 3
    },
    {
        "Id": 51,
        "Name": "Shadow Vanguard - Tenebrion",
        "Desc": "Kamui: Tenebrion Coating - Shadow Vanguard",
        "ConsumeId": 5,
        "ConsumeCount": 98,
        "RewardId": 6610305,
        "ConditionId": [],
        "TimeToEffectStr": "2021/9/9 2:00",
        "TimeToInvalidStr": "2021/10/11 7:59",
        "BuyLimitTimes": 1,
        "BuyLimitType": 0,
        "Icon": "UioPifu51",
        "Tag": 14,
        "UiType": 7,
        "Priority": 20220,
        "LogType": 3
    },
    {
        "Id": 52,
        "Name": "Serum Daily Supply Plan",
        "Desc": "Serum Daily Supply Plan",
        "RewardId": 90091,
        "ConditionId": [],
        "TimeToEffectStr": "2021/9/20 8:00",
        "TimeToInvalidStr": "2021/10/4 6:59",
        "BuyLimitTimes": 1,
        "BuyLimitType": 1,
        "BuyLimitParam": 10000,
        "Icon": "UioDay",
        "IsSellOutShow": 1,
        "Tag": 10,
        "UiType": 6,
        "Priority": 5000,
        "LogType": 3
    },
    {
        "Id": 1004,
        "Name": "[Teatime] Blueprint Bundle",
        "Desc": "[Teatime] Blueprint Bundle",
        "ConsumeId": 5,
        "ConsumeCount": 20,
        "RewardId": 90034,
        "ConditionId": [],
        "TimeToEffectStr": "2021/9/9 2:00",
        "TimeToInvalidStr": "2021/10/11 7:59",
        "BuyLimitTimes": 1,
        "BuyLimitType": 0,
        "Icon": "Uiojiaju47",
        "Tag": 14,
        "UiType": 7,
        "Priority": 30240,
        "LogType": 3
    },
    {
        "Id": 1005,
        "Name": "[Teatime] Set Bundle",
        "Desc": "[Teatime] Set Bundle",
        "ConsumeId": 5,
        "ConsumeCount": 68,
        "RewardId": 90035,
        "ConditionId": [],
        "TimeToEffectStr": "2021/9/9 2:00",
        "TimeToInvalidStr": "2021/10/11 7:59",
        "BuyLimitTimes": 1,
        "BuyLimitType": 0,
        "Icon": "Uiojiaju48",
        "Tag": 14,
        "UiType": 7,
        "Priority": 30250,
        "LogType": 3
    },
    {
        "Id": 83001,
        "Name": "ブーストパック",
        "Desc": "ブーストパック",
        "ConsumeId": 5,
        "ConsumeCount": 100,
        "RewardId": 2000000,
        "ConditionId": [],
        "TimeToEffectStr": "2019/1/1 5:00",
        "TimeToInvalidStr": "2020/1/1 9:59",
        "BuyLimitTimes": 1,
        "BuyLimitType": 0,
        "Icon": "UiPurchaseIconDh648",
        "UiType": 6,
        "Priority": 12000,
        "LogType": 3
    },
    {
        "Id": 83002,
        "Name": "ブーストパック",
        "Desc": "ブーストパック",
        "ConsumeId": 5,
        "ConsumeCount": 100,
        "RewardId": 2000001,
        "PrePurchaseId": 83001,
        "ConditionId": [],
        "TimeToEffectStr": "2019/1/1 5:00",
        "TimeToInvalidStr": "2020/1/1 9:59",
        "BuyLimitTimes": 1,
        "BuyLimitType": 0,
        "Icon": "UiPurchaseIconDh648",
        "UiType": 6,
        "Priority": 11999,
        "LogType": 3
    },
    {
        "Id": 83003,
        "Name": "ブーストパック",
        "Desc": "ブーストパック",
        "ConsumeId": 5,
        "ConsumeCount": 100,
        "RewardId": 2000002,
        "PrePurchaseId": 83002,
        "ConditionId": [],
        "TimeToEffectStr": "2019/1/1 5:00",
        "TimeToInvalidStr": "2020/1/1 9:59",
        "BuyLimitTimes": 1,
        "BuyLimitType": 0,
        "Icon": "UiPurchaseIconDh648",
        "UiType": 6,
        "Priority": 11998,
        "LogType": 3
    },
    {
        "Id": 83004,
        "Name": "オトクパック",
        "Desc": "オトクパック",
        "ConsumeId": 5,
        "ConsumeCount": 5,
        "RewardId": 2000003,
        "ConditionId": [],
        "TimeToEffectStr": "2019/1/1 5:00",
        "TimeToInvalidStr": "2020/1/1 9:59",
        "BuyLimitTimes": 1,
        "BuyLimitType": 1,
        "BuyLimitParam": 10000,
        "Icon": "UiPurchaseIconDh30",
        "UiType": 6,
        "Priority": 11997,
        "LogType": 3
    },
    {
        "Id": 83005,
        "Name": "Newbie Bundle",
        "Desc": "Newbie Bundle",
        "ConsumeId": 3,
        "ConsumeCount": 30,
        "RewardId": 2000004,
        "ConditionId": [],
        "TimeToEffectStr": "2021/6/25 2:00",
        "TimeToInvalidStr": "2021/7/5 23:59",
        "BuyLimitTimes": 1,
        "BuyLimitType": 0,
        "Icon": "UiB25",
        "UiType": 5,
        "Priority": 11996,
        "LogType": 3
    },
    {
        "Id": 83006,
        "Name": "Close-beta Bundle",
        "Desc": "Close-beta Bundle",
        "MailId": 11,
        "MailCount": 1,
        "ConditionId": [],
        "TimeToEffectStr": "2021/6/25 2:00",
        "TimeToInvalidStr": "2021/7/5 23:59",
        "BuyLimitTimes": 1,
        "BuyLimitType": 0,
        "Icon": "UiB35",
        "UiType": 5,
        "Priority": 11995,
        "LogType": 3
    },
    {
        "Id": 2000000,
        "Name": "月間カードB",
        "Desc": "1日1枚支給×30日間",
        "RewardId": 2000006,
        "MailId": 13000010,
        "MailCount": 30,
        "ConditionId": [],
        "TimeToEffectStr": "2019/1/1 5:00",
        "TimeToInvalidStr": "2020/1/1 9:59",
        "BuyLimitType": 2,
        "BuyLimitParam": 30,
        "Icon": "UiCardMonthB",
        "IsSellOutShow": 1,
        "UiType": 2,
        "LogType": 2
    },
    {
        "Id": 2000001,
        "Name": "週間カードA",
        "Desc": "1日1枚支給×7日間",
        "RewardId": 2000006,
        "MailId": 13000020,
        "MailCount": 7,
        "ConditionId": [],
        "TimeToEffectStr": "2019/1/1 5:00",
        "TimeToInvalidStr": "2020/1/1 9:59",
        "BuyLimitType": 2,
        "BuyLimitParam": 7,
        "Icon": "UiCardWeekA",
        "IsSellOutShow": 1,
        "UiType": 13,
        "LogType": 2
    },
    {
        "Id": 2000002,
        "Name": "週間カードB",
        "Desc": "1日1枚支給×7日間",
        "RewardId": 2000006,
        "MailId": 13000030,
        "MailCount": 7,
        "ConditionId": [],
        "TimeToEffectStr": "2019/1/1 5:00",
        "TimeToInvalidStr": "2020/1/1 9:59",
        "BuyLimitType": 2,
        "BuyLimitParam": 7,
        "Icon": "UiCardWeekB",
        "IsSellOutShow": 1,
        "UiType": 13,
        "LogType": 2
    },
    {
        "Id": 2000003,
        "Name": "連日券",
        "Desc": "1日1枚支給×3日間",
        "RewardId": 2000006,
        "MailId": 13000040,
        "MailCount": 3,
        "ConditionId": [],
        "TimeToEffectStr": "2019/1/1 5:00",
        "TimeToInvalidStr": "2020/1/1 9:59",
        "BuyLimitType": 2,
        "BuyLimitParam": 3,
        "Icon": "UiCardDay",
        "IsSellOutShow": 1,
        "UiType": 14,
        "LogType": 2
    },
    {
        "Id": 2000004,
        "Name": "Lv25特別パック",
        "Desc": "Lv25特別パック",
        "ConsumeId": 3,
        "ConsumeCount": 30,
        "RewardId": 2000007,
        "ConditionId": [
            8000
        ],
        "TimeToEffectStr": "2019/1/1 5:00",
        "TimeToInvalidStr": "2020/1/1 9:59",
        "BuyLimitTimes": 1,
        "BuyLimitType": 0,
        "Icon": "UiB25",
        "UiType": 6,
        "Priority": 11995,
        "LogType": 4
    },
    {
        "Id": 2000005,
        "Name": "Lv35特別パック",
        "Desc": "Lv35特別パック",
        "ConsumeId": 3,
        "ConsumeCount": 80,
        "RewardId": 2000008,
        "ConditionId": [
            8001
        ],
        "TimeToEffectStr": "2019/1/1 5:00",
        "TimeToInvalidStr": "2020/1/1 9:59",
        "BuyLimitTimes": 1,
        "BuyLimitType": 0,
        "Icon": "UiB35",
        "UiType": 6,
        "Priority": 11996,
        "LogType": 4
    },
    {
        "Id": 2000006,
        "Name": "Lv45特別パック",
        "Desc": "Lv45特別パック",
        "ConsumeId": 3,
        "ConsumeCount": 150,
        "RewardId": 2000009,
        "ConditionId": [
            8002
        ],
        "TimeToEffectStr": "2019/1/1 5:00",
        "TimeToInvalidStr": "2020/1/1 9:59",
        "BuyLimitTimes": 1,
        "BuyLimitType": 0,
        "Icon": "UiB55",
        "UiType": 6,
        "Priority": 11997,
        "LogType": 4
    },
    {
        "Id": 2000007,
        "Name": "Lv55特別パック",
        "Desc": "Lv55特別パック",
        "ConsumeId": 3,
        "ConsumeCount": 250,
        "RewardId": 2000010,
        "ConditionId": [
            8003
        ],
        "TimeToEffectStr": "2019/1/1 5:00",
        "TimeToInvalidStr": "2020/1/1 9:59",
        "BuyLimitTimes": 1,
        "BuyLimitType": 0,
        "Icon": "UiB70",
        "UiType": 6,
        "Priority": 11998,
        "LogType": 4
    },
    {
        "Id": 2000008,
        "Name": "角色研发补给",
        "Desc": "角色研发补给",
        "RewardId": 2000074,
        "ConditionId": [],
        "TimeToEffectStr": "2019/1/1 5:00",
        "TimeToInvalidStr": "2020/1/1 9:59",
        "BuyLimitTimes": 1,
        "BuyLimitType": 0,
        "Icon": "UiB25",
        "UiType": 6,
        "Priority": 11000,
        "LogType": 4
    },
    {
        "Id": 2000009,
        "Name": "Monthly 6★ Memory Shard Pack",
        "Desc": "Monthly 6★ Memory Shard Pack",
        "ConsumeId": 5,
        "ConsumeCount": 34,
        "RewardId": 2000075,
        "ConditionId": [],
        "TimeToEffectStr": "2021/8/3 7:00",
        "BuyLimitTimes": 1,
        "BuyLimitType": 1,
        "BuyLimitParam": 10004,
        "Icon": "En_Libao06",
        "IsSellOutShow": 1,
        "Tag": 1,
        "UiType": 5,
        "Priority": 10500,
        "LogType": 3
    },
    {
        "Id": 2000010,
        "Name": "超高性价比材料补给",
        "Desc": "超高性价比材料补给",
        "RewardId": 2000076,
        "ConditionId": [],
        "TimeToEffectStr": "2019/1/1 5:00",
        "TimeToInvalidStr": "2020/1/1 9:59",
        "BuyLimitTimes": 1,
        "BuyLimitType": 0,
        "Icon": "UiB25",
        "UiType": 6,
        "Priority": 11002,
        "LogType": 4
    },
    {
        "Id": 2000011,
        "Name": "武器狙击礼包",
        "Desc": "武器狙击礼包",
        "RewardId": 2000077,
        "ConditionId": [],
        "TimeToEffectStr": "2019/1/1 5:00",
        "TimeToInvalidStr": "2020/1/1 9:59",
        "BuyLimitTimes": 1,
        "BuyLimitType": 0,
        "Icon": "UiB25",
        "UiType": 6,
        "Priority": 11003,
        "LogType": 4
    },
    {
        "Id": 2000012,
        "Name": "每月活动角色研发卷",
        "Desc": "每月活动角色研发卷",
        "RewardId": 2000078,
        "ConditionId": [],
        "TimeToEffectStr": "2019/1/1 5:00",
        "TimeToInvalidStr": "2020/1/1 9:59",
        "BuyLimitTimes": 1,
        "BuyLimitType": 0,
        "Icon": "UiB25",
        "UiType": 6,
        "Priority": 11004,
        "LogType": 4
    },
    {
        "Id": 2000013,
        "Name": "每周性价比礼包",
        "Desc": "每周性价比礼包",
        "RewardId": 2000079,
        "ConditionId": [],
        "TimeToEffectStr": "2019/1/1 5:00",
        "TimeToInvalidStr": "2020/1/1 9:59",
        "BuyLimitTimes": 1,
        "BuyLimitType": 0,
        "Icon": "UiB25",
        "UiType": 6,
        "Priority": 11005,
        "LogType": 4
    },
    {
        "Id": 83011,
        "Name": "塗装選択パック",
        "Desc": "塗装選択パック",
        "RewardId": 2000070,
        "ConditionId": [],
        "TimeToEffectStr": "2019/1/1 5:00",
        "TimeToInvalidStr": "2020/1/1 9:59",
        "BuyLimitTimes": 1,
        "BuyLimitType": 0,
        "Icon": "Jp_Libao1",
        "UiType": 7,
        "Priority": 30100,
        "LogType": 3
    },
    {
        "Id": 83012,
        "Name": "サイバー家具図面パック",
        "Desc": "サイバー家具図面パック",
        "RewardId": 2000071,
        "ConditionId": [],
        "TimeToEffectStr": "2019/1/1 5:00",
        "TimeToInvalidStr": "2020/1/1 9:59",
        "BuyLimitTimes": 1,
        "BuyLimitType": 0,
        "Icon": "Jp_Libao2",
        "UiType": 7,
        "Priority": 30250,
        "LogType": 3
    },
    {
        "Id": 83013,
        "Name": "カフェ風家具図面パック",
        "Desc": "カフェ風家具図面パック",
        "RewardId": 2000013,
        "ConditionId": [],
        "TimeToEffectStr": "2019/1/1 5:00",
        "TimeToInvalidStr": "2020/1/1 9:59",
        "BuyLimitTimes": 1,
        "BuyLimitType": 0,
        "Icon": "Jp_Libao3",
        "UiType": 7,
        "Priority": 30350,
        "LogType": 3
    },
    {
        "Id": 83014,
        "Name": "カフェ風家具フルパック",
        "Desc": "カフェ風家具フルパック",
        "RewardId": 2000015,
        "ConditionId": [],
        "TimeToEffectStr": "2019/1/1 5:00",
        "TimeToInvalidStr": "2020/1/1 9:59",
        "BuyLimitTimes": 1,
        "BuyLimitType": 0,
        "Icon": "Jp_Libao4",
        "UiType": 7,
        "Priority": 30300,
        "LogType": 3
    },
    {
        "Id": 83015,
        "Name": "Lv25応援パック",
        "Desc": "Lv25応援パック",
        "RewardId": 2000030,
        "ConditionId": [
            8000
        ],
        "TimeToEffectStr": "2019/1/1 5:00",
        "TimeToInvalidStr": "2020/1/1 9:59",
        "BuyLimitTimes": 1,
        "BuyLimitType": 0,
        "Icon": "Jp_Libao5",
        "UiType": 6,
        "Priority": 11100,
        "LogType": 3
    },
    {
        "Id": 83016,
        "Name": "Lv35応援パック",
        "Desc": "Lv35応援パック",
        "RewardId": 2000019,
        "PrePurchaseId": 83015,
        "ConditionId": [
            8001
        ],
        "TimeToEffectStr": "2019/1/1 5:00",
        "TimeToInvalidStr": "2020/1/1 9:59",
        "BuyLimitTimes": 1,
        "BuyLimitType": 0,
        "Icon": "Jp_Libao6",
        "UiType": 6,
        "Priority": 11300,
        "LogType": 3
    },
    {
        "Id": 83017,
        "Name": "Lv45応援パック",
        "Desc": "Lv45応援パック",
        "RewardId": 2000021,
        "PrePurchaseId": 83016,
        "ConditionId": [
            8002
        ],
        "TimeToEffectStr": "2019/1/1 5:00",
        "TimeToInvalidStr": "2020/1/1 9:59",
        "BuyLimitTimes": 1,
        "BuyLimitType": 0,
        "Icon": "Jp_Libao7",
        "UiType": 6,
        "Priority": 11500,
        "LogType": 3
    },
    {
        "Id": 83018,
        "Name": "Lv55応援パック",
        "Desc": "Lv55応援パック",
        "RewardId": 2000023,
        "PrePurchaseId": 83017,
        "ConditionId": [
            8003
        ],
        "TimeToEffectStr": "2019/1/1 5:00",
        "TimeToInvalidStr": "2020/1/1 9:59",
        "BuyLimitTimes": 1,
        "BuyLimitType": 0,
        "Icon": "Jp_Libao8",
        "UiType": 6,
        "Priority": 11700,
        "LogType": 3
    },
    {
        "Id": 83019,
        "Name": "週間カードA",
        "Desc": "1日1セット支給×7日間",
        "MailId": 13000050,
        "MailCount": 7,
        "ConditionId": [],
        "TimeToEffectStr": "2019/1/1 5:00",
        "TimeToInvalidStr": "2020/1/1 9:59",
        "BuyLimitType": 2,
        "BuyLimitParam": 7,
        "Icon": "Jp_WeeksCardA",
        "IsSellOutShow": 1,
        "UiType": 13,
        "LogType": 2
    },
    {
        "Id": 83020,
        "Name": "週間カードB",
        "Desc": "1日1セット支給×7日間",
        "MailId": 13000060,
        "MailCount": 7,
        "ConditionId": [],
        "TimeToEffectStr": "2019/1/1 5:00",
        "TimeToInvalidStr": "2020/1/1 9:59",
        "BuyLimitType": 2,
        "BuyLimitParam": 7,
        "Icon": "Jp_WeeksCardB",
        "IsSellOutShow": 1,
        "UiType": 13,
        "LogType": 2
    },
    {
        "Id": 83021,
        "Name": "初心者武器開発パック",
        "Desc": "1日1枚支給×10日間",
        "RewardId": 2000024,
        "MailId": 13000070,
        "MailCount": 10,
        "ConditionId": [],
        "TimeToEffectStr": "2019/1/1 5:00",
        "TimeToInvalidStr": "2020/1/1 9:59",
        "BuyLimitTimes": 1,
        "BuyLimitType": 0,
        "Icon": "UioWDrew",
        "Tag": 2,
        "UiType": 5,
        "Priority": 10000,
        "LogType": 3
    },
    {
        "Id": 83022,
        "Name": "月間星6意識パック",
        "Desc": "月間星6意識パック",
        "RewardId": 2000025,
        "ConditionId": [],
        "TimeToEffectStr": "2019/1/1 5:00",
        "TimeToInvalidStr": "2020/1/1 9:59",
        "BuyLimitTimes": 3,
        "BuyLimitType": 1,
        "BuyLimitParam": 10004,
        "Icon": "UiLieche05",
        "IsSellOutShow": 1,
        "UiType": 5,
        "Priority": 10200,
        "LogType": 3
    },
    {
        "Id": 83023,
        "Name": "初心者開発パック",
        "Desc": "初心者開発パック",
        "RewardId": 2000026,
        "ConditionId": [],
        "TimeToEffectStr": "2019/1/1 5:00",
        "TimeToInvalidStr": "2020/1/1 9:59",
        "BuyLimitTimes": 2,
        "BuyLimitType": 0,
        "Icon": "Jp_Libao9",
        "UiType": 5,
        "Priority": 10100,
        "LogType": 3
    },
    {
        "Id": 83024,
        "Name": "初心者5日パス",
        "Desc": "1日1セット支給×5日間",
        "MailId": 13000080,
        "MailCount": 5,
        "ConditionId": [],
        "TimeToEffectStr": "2019/1/1 5:00",
        "TimeToInvalidStr": "2020/1/1 9:59",
        "BuyLimitTimes": 1,
        "BuyLimitType": 0,
        "Icon": "Jp_DaysCard5",
        "UiType": 14,
        "Priority": 13000,
        "LogType": 3
    },
    {
        "Id": 83025,
        "Name": "初心者お得パック",
        "Desc": "初心者お得パック",
        "RewardId": 2000027,
        "ConditionId": [],
        "TimeToEffectStr": "2019/1/1 5:00",
        "TimeToInvalidStr": "2020/1/1 9:59",
        "BuyLimitTimes": 1,
        "BuyLimitType": 0,
        "Icon": "Jp_Libao10",
        "UiType": 5,
        "Priority": 11000,
        "LogType": 3
    },
    {
        "Id": 83026,
        "Name": "限定武器開発パック",
        "Desc": "限定武器開発パック",
        "RewardId": 2000028,
        "ConditionId": [],
        "TimeToEffectStr": "2019/1/1 5:00",
        "TimeToInvalidStr": "2020/1/1 9:59",
        "BuyLimitTimes": 1,
        "BuyLimitType": 0,
        "Icon": "Jp_Libao11",
        "UiType": 5,
        "Priority": 10650,
        "LogType": 3
    },
    {
        "Id": 83027,
        "Name": "週間お得パック",
        "Desc": "週間お得パック",
        "RewardId": 2000029,
        "ConditionId": [],
        "TimeToEffectStr": "2019/1/1 5:00",
        "TimeToInvalidStr": "2020/1/1 9:59",
        "BuyLimitTimes": 1,
        "BuyLimitType": 1,
        "BuyLimitParam": 10001,
        "Icon": "Jp_Libao12",
        "IsSellOutShow": 1,
        "UiType": 5,
        "Priority": 12000,
        "LogType": 3
    },
    {
        "Id": 83028,
        "Name": "Monthly Pass A",
        "Desc": "Sign-in daily to get a total of <color=#ff8338>100</color> Black Cards",
        "ConsumeId": 5,
        "ConsumeCount": 30,
        "RewardId": 2000058,
        "DailyRewardId": 2000102,
        "DailyRewardCount": 30,
        "ConditionId": [],
        "TimeToEffectStr": "2021/7/15 7:00",
        "BuyLimitType": 3,
        "BuyLimitParam": 30,
        "Icon": "Card",
        "IsSellOutShow": 1,
        "Tag": 1,
        "UiType": 2,
        "LogType": 2,
        "MutexPurchaseIdStr": 90032
    },
    {
        "Id": 83029,
        "Name": "Monthly Pass B",
        "Desc": "1 per day for 30 days",
        "ConsumeId": 5,
        "ConsumeCount": 69,
        "RewardId": 2000032,
        "MailId": 13000100,
        "MailCount": 30,
        "ConditionId": [],
        "TimeToEffectStr": "2021/7/15 7:00",
        "BuyLimitType": 2,
        "BuyLimitParam": 30,
        "Icon": "Jp_MonthsCardA",
        "IsSellOutShow": 1,
        "Tag": 1,
        "UiType": 2,
        "LogType": 2
    },
    {
        "Id": 83030,
        "Name": "時計仕掛けのメイドA",
        "Desc": "時計仕掛けのメイドA",
        "RewardId": 2000033,
        "ConditionId": [],
        "TimeToEffectStr": "2019/1/1 5:00",
        "TimeToInvalidStr": "2020/1/1 9:59",
        "BuyLimitTimes": 1,
        "BuyLimitType": 0,
        "Icon": "Jp_Libao13",
        "UiType": 7,
        "Priority": 130400,
        "LogType": 3
    },
    {
        "Id": 83031,
        "Name": "灰羽·重力A",
        "Desc": "灰羽·重力A",
        "RewardId": 2000034,
        "ConditionId": [],
        "TimeToEffectStr": "2019/1/1 5:00",
        "TimeToInvalidStr": "2020/1/1 9:59",
        "BuyLimitTimes": 1,
        "BuyLimitType": 0,
        "Icon": "Jp_Libao14",
        "UiType": 7,
        "Priority": 130500,
        "LogType": 3
    },
    {
        "Id": 83032,
        "Name": "灰羽·夜刃A",
        "Desc": "灰羽·夜刃A",
        "RewardId": 2000035,
        "ConditionId": [],
        "TimeToEffectStr": "2019/1/1 5:00",
        "TimeToInvalidStr": "2020/1/1 9:59",
        "BuyLimitTimes": 1,
        "BuyLimitType": 0,
        "Icon": "Jp_Libao14",
        "UiType": 7,
        "Priority": 130600,
        "LogType": 3
    },
    {
        "Id": 83033,
        "Name": "灰羽·爆裂A",
        "Desc": "灰羽·爆裂A",
        "RewardId": 2000036,
        "ConditionId": [],
        "TimeToEffectStr": "2019/1/1 5:00",
        "TimeToInvalidStr": "2020/1/1 9:59",
        "BuyLimitTimes": 1,
        "BuyLimitType": 0,
        "Icon": "Jp_Libao14",
        "UiType": 7,
        "Priority": 130700,
        "LogType": 3
    },
    {
        "Id": 83034,
        "Name": "灰羽·異火A",
        "Desc": "灰羽·異火A",
        "RewardId": 2000037,
        "ConditionId": [],
        "TimeToEffectStr": "2019/1/1 5:00",
        "TimeToInvalidStr": "2020/1/1 9:59",
        "BuyLimitTimes": 1,
        "BuyLimitType": 0,
        "Icon": "Jp_Libao14",
        "UiType": 7,
        "Priority": 130800,
        "LogType": 3
    },
    {
        "Id": 83035,
        "Name": "灰羽·狂風A",
        "Desc": "灰羽·狂風A",
        "RewardId": 2000039,
        "ConditionId": [],
        "TimeToEffectStr": "2019/1/1 5:00",
        "TimeToInvalidStr": "2020/1/1 9:59",
        "BuyLimitTimes": 1,
        "BuyLimitType": 0,
        "Icon": "Jp_Libao14",
        "UiType": 7,
        "Priority": 130900,
        "LogType": 3
    },
    {
        "Id": 83036,
        "Name": "灰羽·乱数A",
        "Desc": "灰羽·乱数A",
        "RewardId": 2000040,
        "ConditionId": [],
        "TimeToEffectStr": "2019/1/1 5:00",
        "TimeToInvalidStr": "2020/1/1 9:59",
        "BuyLimitTimes": 1,
        "BuyLimitType": 0,
        "Icon": "Jp_Libao14",
        "UiType": 7,
        "Priority": 131000,
        "LogType": 3
    },
    {
        "Id": 83037,
        "Name": "灰羽·黎明A",
        "Desc": "灰羽·黎明A",
        "RewardId": 2000045,
        "ConditionId": [],
        "TimeToEffectStr": "2019/1/1 5:00",
        "TimeToInvalidStr": "2020/1/1 9:59",
        "BuyLimitTimes": 1,
        "BuyLimitType": 0,
        "Icon": "Jp_Libao14",
        "UiType": 7,
        "Priority": 131100,
        "LogType": 3
    },
    {
        "Id": 83038,
        "Name": "綺羅星A",
        "Desc": "綺羅星A",
        "RewardId": 2000046,
        "ConditionId": [],
        "TimeToEffectStr": "2019/1/1 5:00",
        "TimeToInvalidStr": "2020/1/1 9:59",
        "BuyLimitTimes": 1,
        "BuyLimitType": 0,
        "Icon": "Jp_Libao13",
        "UiType": 7,
        "Priority": 130410,
        "LogType": 3
    },
    {
        "Id": 83039,
        "Name": "ゴシック兵A",
        "Desc": "ゴシック兵A",
        "RewardId": 2000047,
        "ConditionId": [],
        "TimeToEffectStr": "2019/1/1 5:00",
        "TimeToInvalidStr": "2020/1/1 9:59",
        "BuyLimitTimes": 1,
        "BuyLimitType": 0,
        "Icon": "Jp_Libao13",
        "UiType": 7,
        "Priority": 130420,
        "LogType": 3
    },
    {
        "Id": 83040,
        "Name": "終焉の灰燼A",
        "Desc": "終焉の灰燼A",
        "RewardId": 2000048,
        "ConditionId": [],
        "TimeToEffectStr": "2019/1/1 5:00",
        "TimeToInvalidStr": "2020/1/1 9:59",
        "BuyLimitTimes": 1,
        "BuyLimitType": 0,
        "Icon": "Jp_Libao13",
        "UiType": 7,
        "Priority": 130430,
        "LogType": 3
    },
    {
        "Id": 83041,
        "Name": "3日パス",
        "Desc": "1日1セット支給×3日間",
        "MailId": 13000090,
        "MailCount": 3,
        "ConditionId": [],
        "TimeToEffectStr": "2019/1/1 5:00",
        "TimeToInvalidStr": "2020/1/1 9:59",
        "BuyLimitType": 2,
        "BuyLimitParam": 3,
        "Icon": "Jp_DaysCard3",
        "IsSellOutShow": 1,
        "UiType": 14,
        "Priority": 30100,
        "LogType": 3
    },
    {
        "Id": 83042,
        "Name": "週間無料補給パック",
        "Desc": "週間無料補給パック",
        "RewardId": 2000049,
        "ConditionId": [],
        "TimeToEffectStr": "2019/1/1 5:00",
        "TimeToInvalidStr": "2020/1/1 9:59",
        "BuyLimitTimes": 1,
        "BuyLimitType": 1,
        "BuyLimitParam": 10001,
        "Icon": "UioWeek",
        "IsSellOutShow": 1,
        "Tag": 10,
        "UiType": 6,
        "Priority": 5000,
        "LogType": 3
    },
    {
        "Id": 83043,
        "Name": "月間特別武器開発パック",
        "Desc": "月間武器開発券",
        "RewardId": 2000054,
        "ConditionId": [],
        "TimeToEffectStr": "2019/1/1 5:00",
        "TimeToInvalidStr": "2020/1/1 9:59",
        "BuyLimitTimes": 1,
        "BuyLimitType": 1,
        "BuyLimitParam": 10004,
        "Icon": "UioWDMouth",
        "IsSellOutShow": 1,
        "Tag": 1,
        "UiType": 5,
        "Priority": 10700,
        "LogType": 3
    },
    {
        "Id": 83044,
        "Name": "月間特別構造体開発パック",
        "Desc": "月間特別構造体開発パック",
        "RewardId": 2000055,
        "ConditionId": [],
        "TimeToEffectStr": "2019/1/1 5:00",
        "TimeToInvalidStr": "2020/1/1 9:59",
        "BuyLimitTimes": 1,
        "BuyLimitType": 1,
        "BuyLimitParam": 10004,
        "Icon": "UioCDMouth2",
        "IsSellOutShow": 1,
        "Tag": 1,
        "UiType": 5,
        "Priority": 10600,
        "LogType": 3
    },
    {
        "Id": 83045,
        "Name": "塗装設計図パック",
        "Desc": "塗装設計図パック",
        "RewardId": 2000056,
        "ConditionId": [],
        "TimeToEffectStr": "2019/1/1 5:00",
        "TimeToInvalidStr": "2020/1/1 9:59",
        "Icon": "UioSkinD",
        "IsSellOutShow": 0,
        "UiType": 7,
        "Priority": 30500,
        "LogType": 3
    },
    {
        "Id": 83046,
        "Name": "ネジパック",
        "Desc": "ネジパック",
        "RewardId": 2000057,
        "ConditionId": [],
        "TimeToEffectStr": "2019/1/1 5:00",
        "TimeToInvalidStr": "2020/1/1 9:59",
        "Icon": "UioFCoin",
        "IsSellOutShow": 0,
        "UiType": 7,
        "Priority": 50500,
        "LogType": 3
    },
    {
        "Id": 83047,
        "Name": "週間育成パック",
        "Desc": "週間育成パック",
        "RewardId": 2000059,
        "ConditionId": [],
        "TimeToEffectStr": "2019/1/1 5:00",
        "TimeToInvalidStr": "2020/1/1 9:59",
        "BuyLimitTimes": 1,
        "BuyLimitType": 1,
        "BuyLimitParam": 10001,
        "Icon": "UioXingjia",
        "IsSellOutShow": 1,
        "UiType": 6,
        "Priority": 10800,
        "LogType": 3
    },
    {
        "Id": 83048,
        "Name": "月間塗装設計図パック",
        "Desc": "月間塗装設計図パック",
        "RewardId": 2000060,
        "ConditionId": [],
        "TimeToEffectStr": "2019/1/1 5:00",
        "TimeToInvalidStr": "2020/1/1 9:59",
        "BuyLimitTimes": 1,
        "BuyLimitType": 1,
        "BuyLimitParam": 10004,
        "Icon": "UioPifuM",
        "IsSellOutShow": 1,
        "UiType": 7,
        "Priority": 30500,
        "LogType": 3
    },
    {
        "Id": 83049,
        "Name": "塗装パック-銀庭の花冠",
        "Desc": "塗装パック-銀庭の花冠",
        "RewardId": 2000061,
        "ConditionId": [],
        "TimeToEffectStr": "2019/1/1 5:00",
        "TimeToInvalidStr": "2020/1/1 9:59",
        "BuyLimitTimes": 1,
        "BuyLimitType": 0,
        "Icon": "UioLifu",
        "Tag": 1,
        "UiType": 7,
        "Priority": 30000,
        "LogType": 3
    },
    {
        "Id": 83050,
        "Name": "サイバー家具フルパック",
        "Desc": "サイバー家具フルパック",
        "RewardId": 2000062,
        "ConditionId": [],
        "TimeToEffectStr": "2019/1/1 5:00",
        "TimeToInvalidStr": "2020/1/1 9:59",
        "BuyLimitTimes": 1,
        "BuyLimitType": 0,
        "Icon": "UioNF",
        "UiType": 7,
        "Priority": 30200,
        "LogType": 3
    },
    {
        "Id": 83051,
        "Name": "塗装設計図パックA",
        "Desc": "塗装設計図パックA",
        "RewardId": 2000090,
        "ConditionId": [],
        "TimeToEffectStr": "2019/1/1 5:00",
        "TimeToInvalidStr": "2020/1/1 9:59",
        "Icon": "UioSkinD",
        "IsSellOutShow": 0,
        "UiType": 7,
        "Priority": 150400,
        "LogType": 3
    },
    {
        "Id": 83052,
        "Name": "初心者開発パックA",
        "Desc": "初心者開発パックA",
        "RewardId": 2000091,
        "ConditionId": [],
        "TimeToEffectStr": "2019/1/1 5:00",
        "TimeToInvalidStr": "2020/1/1 9:59",
        "BuyLimitTimes": 2,
        "BuyLimitType": 0,
        "Icon": "Jp_Libao9",
        "UiType": 5,
        "Priority": 110100,
        "LogType": 3
    },
    {
        "Id": 83053,
        "Name": "週間お得パックA",
        "Desc": "週間お得パックA",
        "RewardId": 2000092,
        "ConditionId": [],
        "TimeToEffectStr": "2019/1/1 5:00",
        "TimeToInvalidStr": "2020/1/1 9:59",
        "BuyLimitTimes": 1,
        "BuyLimitType": 1,
        "BuyLimitParam": 10001,
        "Icon": "Jp_Libao12",
        "IsSellOutShow": 1,
        "UiType": 5,
        "Priority": 112000,
        "LogType": 3
    },
    {
        "Id": 83054,
        "Name": "ネジパックA",
        "Desc": "ネジパックA",
        "RewardId": 2000093,
        "ConditionId": [],
        "TimeToEffectStr": "2019/1/1 5:00",
        "TimeToInvalidStr": "2020/1/1 9:59",
        "Icon": "UioFCoin",
        "IsSellOutShow": 0,
        "UiType": 7,
        "Priority": 150500,
        "LogType": 3
    },
    {
        "Id": 83055,
        "Name": "月間特別構造体開発パックA",
        "Desc": "月間特別構造体開発パックA",
        "RewardId": 2000094,
        "ConditionId": [],
        "TimeToEffectStr": "2019/1/1 5:00",
        "TimeToInvalidStr": "2020/1/1 9:59",
        "BuyLimitTimes": 1,
        "BuyLimitType": 1,
        "BuyLimitParam": 10004,
        "Icon": "UioCDMouth2",
        "IsSellOutShow": 1,
        "Tag": 1,
        "UiType": 5,
        "Priority": 110600,
        "LogType": 3
    },
    {
        "Id": 83056,
        "Name": "週間補給パックA",
        "Desc": "週間補給パックA",
        "RewardId": 2000095,
        "ConditionId": [],
        "TimeToEffectStr": "2019/1/1 5:00",
        "TimeToInvalidStr": "2020/1/1 9:59",
        "BuyLimitTimes": 1,
        "BuyLimitType": 1,
        "BuyLimitParam": 10001,
        "Icon": "UioWeek",
        "IsSellOutShow": 1,
        "Tag": 1,
        "UiType": 6,
        "Priority": 15000,
        "LogType": 3
    },
    {
        "Id": 83057,
        "Name": "週間強化パックA",
        "Desc": "週間強化パックA",
        "RewardId": 2000067,
        "ConditionId": [],
        "TimeToEffectStr": "2019/1/1 5:00",
        "TimeToInvalidStr": "2020/1/1 9:59",
        "BuyLimitTimes": 1,
        "BuyLimitType": 1,
        "BuyLimitParam": 10001,
        "Icon": "UioWeek",
        "IsSellOutShow": 1,
        "Tag": 1,
        "UiType": 6,
        "Priority": 16000,
        "LogType": 3
    },
    {
        "Id": 83058,
        "Name": "カフェ風家具図面パックA",
        "Desc": "カフェ風家具図面パックA",
        "RewardId": 2000096,
        "ConditionId": [],
        "TimeToEffectStr": "2019/1/1 5:00",
        "TimeToInvalidStr": "2020/1/1 9:59",
        "BuyLimitTimes": 1,
        "BuyLimitType": 0,
        "Icon": "Jp_Libao3",
        "UiType": 7,
        "Priority": 130350,
        "LogType": 3
    },
    {
        "Id": 83059,
        "Name": "カフェ風家具フルパックA",
        "Desc": "カフェ風家具フルパックA",
        "RewardId": 2000098,
        "ConditionId": [],
        "TimeToEffectStr": "2019/1/1 5:00",
        "TimeToInvalidStr": "2020/1/1 9:59",
        "BuyLimitTimes": 1,
        "BuyLimitType": 0,
        "Icon": "Jp_Libao4",
        "UiType": 7,
        "Priority": 130300,
        "LogType": 3
    },
    {
        "Id": 83060,
        "Name": "アザミA",
        "Desc": "アザミA",
        "RewardId": 2000080,
        "ConditionId": [],
        "TimeToEffectStr": "2019/1/1 5:00",
        "TimeToInvalidStr": "2020/1/1 9:59",
        "BuyLimitTimes": 1,
        "BuyLimitType": 0,
        "Icon": "Jp_Libao13",
        "UiType": 7,
        "Priority": 130440,
        "LogType": 3
    },
    {
        "Id": 83061,
        "Name": "灰羽·来光A",
        "Desc": "灰羽·来光A",
        "RewardId": 2000081,
        "ConditionId": [],
        "TimeToEffectStr": "2019/1/1 5:00",
        "TimeToInvalidStr": "2020/1/1 9:59",
        "BuyLimitTimes": 1,
        "BuyLimitType": 0,
        "Icon": "Jp_Libao14",
        "UiType": 7,
        "Priority": 130490,
        "LogType": 3
    },
    {
        "Id": 83062,
        "Name": "Lv25応援パックA",
        "Desc": "Lv25応援パックA",
        "RewardId": 2000082,
        "ConditionId": [
            8000
        ],
        "TimeToEffectStr": "2019/1/1 5:00",
        "TimeToInvalidStr": "2020/1/1 9:59",
        "BuyLimitTimes": 1,
        "BuyLimitType": 0,
        "Icon": "Jp_Libao5",
        "UiType": 6,
        "Priority": 111100,
        "LogType": 3
    },
    {
        "Id": 83063,
        "Name": "Lv35応援パックA",
        "Desc": "Lv35応援パックA",
        "RewardId": 2000083,
        "PrePurchaseId": 83062,
        "ConditionId": [
            8001
        ],
        "TimeToEffectStr": "2019/1/1 5:00",
        "TimeToInvalidStr": "2020/1/1 9:59",
        "BuyLimitTimes": 1,
        "BuyLimitType": 0,
        "Icon": "Jp_Libao6",
        "UiType": 6,
        "Priority": 111300,
        "LogType": 3
    },
    {
        "Id": 83064,
        "Name": "Lv45応援パックA",
        "Desc": "Lv45応援パックA",
        "RewardId": 2000084,
        "PrePurchaseId": 83063,
        "ConditionId": [
            8002
        ],
        "TimeToEffectStr": "2019/1/1 5:00",
        "TimeToInvalidStr": "2020/1/1 9:59",
        "BuyLimitTimes": 1,
        "BuyLimitType": 0,
        "Icon": "Jp_Libao7",
        "UiType": 6,
        "Priority": 111500,
        "LogType": 3
    },
    {
        "Id": 83065,
        "Name": "Lv55応援パックA",
        "Desc": "Lv55応援パックA",
        "RewardId": 2000085,
        "PrePurchaseId": 83064,
        "ConditionId": [
            8003
        ],
        "TimeToEffectStr": "2019/1/1 5:00",
        "TimeToInvalidStr": "2020/1/1 9:59",
        "BuyLimitTimes": 1,
        "BuyLimitType": 0,
        "Icon": "Jp_Libao8",
        "UiType": 6,
        "Priority": 111700,
        "LogType": 3
    },
    {
        "Id": 83066,
        "Name": "週間育成パックA",
        "Desc": "週間育成パックA",
        "RewardId": 2000086,
        "ConditionId": [],
        "TimeToEffectStr": "2019/1/1 5:00",
        "TimeToInvalidStr": "2020/1/1 9:59",
        "BuyLimitTimes": 1,
        "BuyLimitType": 1,
        "BuyLimitParam": 10001,
        "Icon": "UioXingjia",
        "IsSellOutShow": 1,
        "UiType": 6,
        "Priority": 110800,
        "LogType": 3
    },
    {
        "Id": 83067,
        "Name": "限定武器開発パックB",
        "Desc": "限定武器開発パックB",
        "RewardId": 2000087,
        "ConditionId": [],
        "TimeToEffectStr": "2019/1/1 5:00",
        "TimeToInvalidStr": "2020/1/1 9:59",
        "BuyLimitTimes": 1,
        "BuyLimitType": 0,
        "Icon": "Jp_Libao11",
        "UiType": 5,
        "Priority": 110650,
        "LogType": 3
    },
    {
        "Id": 83068,
        "Name": "月間特別構造体開発パックB",
        "Desc": "月間特別構造体開発パックB",
        "RewardId": 2000088,
        "ConditionId": [],
        "TimeToEffectStr": "2019/1/1 5:00",
        "TimeToInvalidStr": "2020/1/1 9:59",
        "BuyLimitTimes": 1,
        "BuyLimitType": 1,
        "BuyLimitParam": 10004,
        "Icon": "UioCDMouth2",
        "IsSellOutShow": 1,
        "Tag": 1,
        "UiType": 5,
        "Priority": 110600,
        "LogType": 3
    },
    {
        "Id": 83069,
        "Name": "月間特別武器開発パックA",
        "Desc": "月間特別武器開発パックA",
        "RewardId": 2000089,
        "ConditionId": [],
        "TimeToEffectStr": "2019/1/1 5:00",
        "TimeToInvalidStr": "2020/1/1 9:59",
        "BuyLimitTimes": 1,
        "BuyLimitType": 1,
        "BuyLimitParam": 10004,
        "Icon": "UioWDMouth",
        "IsSellOutShow": 1,
        "Tag": 1,
        "UiType": 5,
        "Priority": 110700,
        "LogType": 3
    },
    {
        "Id": 85900,
        "Name": "新年賽銭パック-1回",
        "RewardId": 2000197,
        "ConditionId": [],
        "TimeToEffectStr": "2021/1/1 0:00",
        "TimeToInvalidStr": "2021/1/7 23:59",
        "Icon": "Jp_Libao32",
        "UiType": 7,
        "Priority": 1006,
        "LogType": 3
    },
    {
        "Id": 85901,
        "Name": "新年賽銭パック-5回",
        "RewardId": 2000198,
        "ConditionId": [],
        "TimeToEffectStr": "2021/1/1 0:00",
        "TimeToInvalidStr": "2021/1/7 23:59",
        "Icon": "Jp_Libao33",
        "UiType": 7,
        "Priority": 1005,
        "LogType": 3
    },
    {
        "Id": 90000,
        "Name": "Gray Feather Series Pick",
        "Desc": "Gray Feather Series Pick",
        "ConsumeId": 5,
        "ConsumeCount": 126,
        "RewardId": 5000033,
        "ConditionId": [],
        "TimeToEffectStr": "2019/1/1 5:00",
        "TimeToInvalidStr": "2020/1/1 9:59",
        "BuyLimitTimes": 3,
        "BuyLimitType": 0,
        "Icon": "UioZhixuan",
        "UiType": 7,
        "Priority": 30100,
        "LogType": 3
    },
    {
        "Id": 90001,
        "Name": "Special Coating Pick",
        "Desc": "Special Coating Pick",
        "ConsumeId": 5,
        "ConsumeCount": 154,
        "RewardId": 5000034,
        "ConditionId": [],
        "TimeToEffectStr": "2019/1/1 5:00",
        "TimeToInvalidStr": "2020/1/1 9:59",
        "BuyLimitTimes": 3,
        "BuyLimitType": 0,
        "Icon": "UioZhixuan",
        "UiType": 7,
        "Priority": 30101,
        "LogType": 3
    },
    {
        "Id": 90002,
        "Name": "Release Value Pack",
        "Desc": "1 per day for 5 days",
        "ConsumeId": 5,
        "ConsumeCount": 129,
        "RewardId": 5000035,
        "MailId": 14000001,
        "MailCount": 5,
        "ConditionId": [],
        "TimeToEffectStr": "2021/7/17 7:00",
        "TimeToInvalidStr": "2021/8/8 23:59",
        "BuyLimitTimes": 1,
        "BuyLimitType": 0,
        "Icon": "En_Libao02",
        "UiType": 5,
        "Priority": 10500,
        "LogType": 3
    },
    {
        "Id": 90003,
        "Name": "Gray Feather Series Pick",
        "Desc": "Gray Feather Series Pick",
        "ConsumeId": 5,
        "ConsumeCount": 126,
        "RewardId": 5000036,
        "ConditionId": [],
        "TimeToEffectStr": "2021/7/17 7:00",
        "TimeToInvalidStr": "2021/8/8 23:59",
        "BuyLimitTimes": 3,
        "BuyLimitType": 0,
        "Icon": "En_Libao01",
        "UiType": 7,
        "Priority": 30100,
        "LogType": 3
    },
    {
        "Id": 90004,
        "Name": "Special Coating Pick",
        "Desc": "Special Coating Pick",
        "ConsumeId": 5,
        "ConsumeCount": 154,
        "RewardId": 5000037,
        "ConditionId": [],
        "TimeToEffectStr": "2021/7/17 7:00",
        "TimeToInvalidStr": "2021/8/8 23:59",
        "BuyLimitTimes": 3,
        "BuyLimitType": 0,
        "Icon": "En_Libao01",
        "UiType": 7,
        "Priority": 30101,
        "LogType": 3
    },
    {
        "Id": 90005,
        "Name": "Release Focus Weapon R&D Pack",
        "Desc": "Release Focus Weapon R&D Pack",
        "ConsumeId": 5,
        "ConsumeCount": 119,
        "RewardId": 5000038,
        "ConditionId": [],
        "TimeToEffectStr": "2021/7/17 7:00",
        "TimeToInvalidStr": "2021/8/8 23:59",
        "BuyLimitTimes": 1,
        "BuyLimitType": 0,
        "Icon": "En_Libao03",
        "IsSellOutShow": 1,
        "Tag": 1,
        "UiType": 5,
        "Priority": 10700,
        "LogType": 3
    },
    {
        "Id": 90006,
        "Name": "Release Event Construct R&D Pack",
        "Desc": "Release Event Construct R&D Pack",
        "ConsumeId": 5,
        "ConsumeCount": 99,
        "RewardId": 5000039,
        "ConditionId": [],
        "TimeToEffectStr": "2021/7/17 7:00",
        "TimeToInvalidStr": "2021/8/8 23:59",
        "BuyLimitTimes": 1,
        "BuyLimitType": 0,
        "Icon": "En_Libao04",
        "IsSellOutShow": 1,
        "Tag": 1,
        "UiType": 5,
        "Priority": 10600,
        "LogType": 3
    },
    {
        "Id": 90007,
        "Name": "Overclock Material Pack",
        "Desc": "Overclock Material Pack",
        "ConsumeId": 5,
        "ConsumeCount": 99,
        "RewardId": 5000040,
        "ConditionId": [],
        "TimeToEffectStr": "2021/7/17 7:00",
        "TimeToInvalidStr": "2021/8/8 23:59",
        "BuyLimitTimes": 2,
        "BuyLimitType": 0,
        "Icon": "En_Libao05",
        "IsSellOutShow": 1,
        "UiType": 5,
        "Priority": 10800,
        "LogType": 3
    },
    {
        "Id": 90008,
        "Name": "6★ Memory Shard Pack",
        "Desc": "6★ Memory Shard Pack",
        "ConsumeId": 5,
        "ConsumeCount": 59,
        "RewardId": 5000041,
        "ConditionId": [],
        "TimeToEffectStr": "2021/7/17 7:00",
        "TimeToInvalidStr": "2021/8/8 23:59",
        "BuyLimitTimes": 1,
        "BuyLimitType": 0,
        "Icon": "En_Libao07",
        "UiType": 6,
        "Priority": 11001,
        "LogType": 3
    },
    {
        "Id": 90009,
        "Name": "Advanced Research Pack",
        "Desc": "Advanced Research Pack",
        "ConsumeId": 5,
        "ConsumeCount": 299,
        "RewardId": 5000043,
        "ConditionId": [],
        "TimeToEffectStr": "2021/7/17 7:00",
        "TimeToInvalidStr": "2021/8/8 23:59",
        "BuyLimitTimes": 1,
        "BuyLimitType": 0,
        "Icon": "En_Libao08",
        "Tag": 1,
        "UiType": 5,
        "Priority": 30102,
        "LogType": 3
    },
    {
        "Id": 90010,
        "Name": "[Frozen] R&D Medium Pack",
        "ConsumeId": 5,
        "ConsumeCount": 119,
        "RewardId": 5000044,
        "ConditionId": [],
        "TimeToEffectStr": "2021/8/3 7:00",
        "TimeToInvalidStr": "2021/9/8 6:59",
        "BuyLimitTimes": 1,
        "BuyLimitType": 0,
        "Icon": "En_Libao09",
        "Tag": 14,
        "UiType": 5,
        "Priority": 2000,
        "LogType": 3
    },
    {
        "Id": 90012,
        "Name": "[Frozen] Weapon R&D Pack",
        "ConsumeId": 5,
        "ConsumeCount": 59,
        "RewardId": 5000046,
        "ConditionId": [],
        "TimeToEffectStr": "2021/8/3 7:00",
        "TimeToInvalidStr": "2021/9/8 6:59",
        "BuyLimitTimes": 2,
        "BuyLimitType": 0,
        "Icon": "En_Libao11",
        "Tag": 14,
        "UiType": 5,
        "Priority": 2002,
        "LogType": 3
    },
    {
        "Id": 90013,
        "Name": "[Frozen] Basic R&D Bundle",
        "ConsumeId": 5,
        "ConsumeCount": 119,
        "RewardId": 5000047,
        "ConditionId": [],
        "TimeToEffectStr": "2021/8/3 7:00",
        "TimeToInvalidStr": "2021/9/8 6:59",
        "BuyLimitTimes": 1,
        "BuyLimitType": 0,
        "Icon": "En_Libao12",
        "Tag": 14,
        "UiType": 5,
        "Priority": 2003,
        "LogType": 3
    },
    {
        "Id": 90015,
        "Name": "Terminal Code - 10x Bundle",
        "Desc": "Terminal Code - 10x Bundle",
        "ConsumeId": 5,
        "ConsumeCount": 99,
        "RewardId": 5000049,
        "ConditionId": [],
        "TimeToEffectStr": "2021/9/10 8:00",
        "TimeToInvalidStr": "2021/9/23 23:59",
        "BuyLimitTimes": 2,
        "BuyLimitType": 0,
        "Icon": "En_Libao24",
        "Tag": 14,
        "UiType": 7,
        "Priority": 2000,
        "LogType": 3
    },
    {
        "Id": 90016,
        "Name": "Terminal Code - 5x Bundle",
        "Desc": "Terminal Code - 5x Bundle",
        "ConsumeId": 5,
        "ConsumeCount": 82,
        "RewardId": 5000050,
        "ConditionId": [],
        "TimeToEffectStr": "2021/9/10 8:00",
        "TimeToInvalidStr": "2021/9/23 23:59",
        "BuyLimitTimes": 8,
        "BuyLimitType": 0,
        "Icon": "ItKrYunying003",
        "Tag": 14,
        "UiType": 7,
        "Priority": 2001,
        "LogType": 3
    },
    {
        "Id": 90017,
        "Name": "Terminal Code - 1 Pull Bundle",
        "Desc": "Terminal Code - 1 Pull Bundle",
        "ConsumeId": 5,
        "ConsumeCount": 20,
        "RewardId": 5000051,
        "ConditionId": [],
        "TimeToEffectStr": "2021/9/10 8:00",
        "TimeToInvalidStr": "2021/9/23 23:59",
        "Icon": "ItKrYunying002",
        "Tag": 14,
        "UiType": 7,
        "Priority": 2002,
        "LogType": 3
    },
    {
        "Id": 90018,
        "Name": "Shrine Visit Welfare",
        "ConsumeId": 3,
        "ConsumeCount": 180,
        "RewardId": 5000052,
        "ConditionId": [],
        "TimeToEffectStr": "2020/8/4 8:00",
        "TimeToInvalidStr": "2020/8/18 7:59",
        "BuyLimitTimes": 5,
        "BuyLimitType": 0,
        "Icon": "Jp_Libao33",
        "Tag": 14,
        "UiType": 7,
        "Priority": 2003,
        "LogType": 3
    },
    {
        "Id": 90019,
        "Name": "Target Weapon R&D Pack - 7d",
        "Desc": "1 per day for 7 days",
        "ConsumeId": 5,
        "ConsumeCount": 59,
        "MailId": 14000002,
        "MailCount": 7,
        "ConditionId": [],
        "TimeToEffectStr": "2021/8/23 7:00",
        "TimeToInvalidStr": "2021/9/6 6:59",
        "BuyLimitTimes": 1,
        "BuyLimitType": 0,
        "Icon": "En_Libao15",
        "Tag": 14,
        "UiType": 6,
        "Priority": 20000,
        "LogType": 3
    },
    {
        "Id": 90020,
        "Name": "Battle Power Supply",
        "ConsumeId": 5,
        "ConsumeCount": 28,
        "RewardId": 5000053,
        "ConditionId": [],
        "TimeToEffectStr": "2021/8/23 7:00",
        "TimeToInvalidStr": "2021/9/6 6:59",
        "BuyLimitTimes": 1,
        "BuyLimitType": 1,
        "BuyLimitParam": 10001,
        "Icon": "En_Libao16",
        "Tag": 14,
        "UiType": 5,
        "Priority": 2004,
        "LogType": 3
    },
    {
        "Id": 90021,
        "Name": "Gray Feather: Crimson Abyss",
        "ConsumeId": 5,
        "ConsumeCount": 126,
        "RewardId": 5000054,
        "ConditionId": [],
        "TimeToEffectStr": "2021/8/4 8:00",
        "TimeToInvalidStr": "2021/9/8 6:59",
        "BuyLimitTimes": 1,
        "BuyLimitType": 0,
        "Icon": "UioPifu43",
        "IsSellOutShow": 1,
        "Tag": 14,
        "UiType": 7,
        "Priority": 2009,
        "LogType": 3
    },
    {
        "Id": 90022,
        "Name": "Gray Feather: Bastion",
        "ConsumeId": 5,
        "ConsumeCount": 126,
        "RewardId": 5000055,
        "ConditionId": [],
        "TimeToEffectStr": "2021/8/3 7:00",
        "TimeToInvalidStr": "2021/9/8 6:59",
        "BuyLimitTimes": 1,
        "BuyLimitType": 0,
        "Icon": "Jp_UioPifu2",
        "IsSellOutShow": 1,
        "Tag": 14,
        "UiType": 7,
        "Priority": 2010,
        "LogType": 3
    },
    {
        "Id": 90023,
        "Name": "End Messenger",
        "ConsumeId": 5,
        "ConsumeCount": 98,
        "RewardId": 5000056,
        "ConditionId": [],
        "TimeToEffectStr": "2021/8/3 7:00",
        "TimeToInvalidStr": "2021/9/8 6:59",
        "BuyLimitTimes": 1,
        "BuyLimitType": 0,
        "Icon": "Jp_UioPifu1",
        "IsSellOutShow": 1,
        "Tag": 14,
        "UiType": 7,
        "Priority": 2012,
        "LogType": 3
    },
    {
        "Id": 90024,
        "Name": "Final Journey",
        "ConsumeId": 5,
        "ConsumeCount": 154,
        "RewardId": 5000064,
        "ConditionId": [],
        "TimeToEffectStr": "2021/8/4 8:00",
        "TimeToInvalidStr": "2021/9/8 6:59",
        "BuyLimitTimes": 1,
        "BuyLimitType": 0,
        "Icon": "UioPifu44",
        "IsSellOutShow": 1,
        "Tag": 14,
        "UiType": 7,
        "Priority": 2011,
        "LogType": 3
    },
    {
        "Id": 90025,
        "Name": "[Fallen] Event R&D Pack",
        "Desc": "[Fallen] Event R&D Pack",
        "ConsumeId": 5,
        "ConsumeCount": 119,
        "RewardId": 5000075,
        "ConditionId": [],
        "TimeToEffectStr": "2021/9/9 2:00",
        "TimeToInvalidStr": "2021/10/11 7:59",
        "BuyLimitTimes": 1,
        "BuyLimitType": 0,
        "Icon": "En_Libao17",
        "Tag": 14,
        "UiType": 5,
        "Priority": 2000,
        "LogType": 3
    },
    {
        "Id": 90026,
        "Name": "[Fallen] Weapon R&D Pack",
        "Desc": "[Fallen] Weapon R&D Pack",
        "ConsumeId": 5,
        "ConsumeCount": 59,
        "RewardId": 5000076,
        "ConditionId": [],
        "TimeToEffectStr": "2021/9/9 2:00",
        "TimeToInvalidStr": "2021/10/11 7:59",
        "BuyLimitTimes": 2,
        "BuyLimitType": 0,
        "Icon": "En_Libao18",
        "Tag": 14,
        "UiType": 5,
        "Priority": 2002,
        "LogType": 3
    },
    {
        "Id": 90027,
        "Name": "[Fallen] Basic R&D Pack",
        "Desc": "[Fallen] Basic R&D Pack",
        "ConsumeId": 5,
        "ConsumeCount": 119,
        "RewardId": 5000077,
        "ConditionId": [],
        "TimeToEffectStr": "2021/9/9 2:00",
        "TimeToInvalidStr": "2021/10/11 7:59",
        "BuyLimitTimes": 1,
        "BuyLimitType": 0,
        "Icon": "En_Libao19",
        "Tag": 14,
        "UiType": 5,
        "Priority": 2003,
        "LogType": 3
    },
    {
        "Id": 90028,
        "Name": "[Fallen] Construct R&D Pack",
        "Desc": "[Fallen] Construct R&D Pack",
        "ConsumeId": 5,
        "ConsumeCount": 119,
        "RewardId": 5000078,
        "ConditionId": [],
        "TimeToEffectStr": "2021/9/9 2:00",
        "TimeToInvalidStr": "2021/10/11 7:59",
        "BuyLimitTimes": 1,
        "BuyLimitType": 0,
        "Icon": "En_Libao20",
        "Tag": 14,
        "UiType": 5,
        "Priority": 2004,
        "LogType": 3
    },
    {
        "Id": 90029,
        "Name": "[Fallen] Serum Weekly Pass",
        "Desc": "1 per day for 7 days",
        "ConsumeId": 5,
        "ConsumeCount": 28,
        "MailId": 14000003,
        "MailCount": 7,
        "ConditionId": [],
        "TimeToEffectStr": "2021/9/9 2:00",
        "TimeToInvalidStr": "2021/10/11 6:59",
        "BuyLimitTimes": 1,
        "BuyLimitType": 1,
        "BuyLimitParam": 10001,
        "Icon": "En_Libao21",
        "Tag": 14,
        "UiType": 5,
        "Priority": 2005,
        "LogType": 3
    },
    {
        "Id": 90030,
        "Name": "A-Rank Male Construct Pack",
        "Desc": "A-Rank Male Construct Pack",
        "ConsumeId": 5,
        "ConsumeCount": 34,
        "RewardId": 5000079,
        "ConditionId": [],
        "TimeToEffectStr": "2021/9/24 8:00",
        "TimeToInvalidStr": "2021/10/11 7:59",
        "BuyLimitTimes": 1,
        "BuyLimitType": 0,
        "Icon": "UiQingrenjie02",
        "Tag": 1,
        "UiType": 5,
        "Priority": 10110,
        "LogType": 3
    },
    {
        "Id": 90031,
        "Name": "A-Rank Female Construct Pack",
        "Desc": "A-Rank Female Construct Pack",
        "ConsumeId": 5,
        "ConsumeCount": 34,
        "RewardId": 5000080,
        "ConditionId": [],
        "TimeToEffectStr": "2021/9/24 8:00",
        "TimeToInvalidStr": "2021/10/11 7:59",
        "BuyLimitTimes": 1,
        "BuyLimitType": 0,
        "Icon": "UiQingrenjie01",
        "Tag": 1,
        "UiType": 5,
        "Priority": 10120,
        "LogType": 3
    },
    {
        "Id": 90032,
        "Name": "Monthly Pass C",
        "Desc": "Sign-in daily to get a total of <color=#ff8338>90</color> Black Cards",
        "ConsumeId": 5,
        "ConsumeCount": 28,
        "RewardId": 2000058,
        "DailyRewardId": 5000084,
        "DailyRewardCount": 30,
        "ConditionId": [],
        "TimeToEffectStr": "2021/7/15 7:00",
        "BuyLimitType": 3,
        "BuyLimitParam": 30,
        "Icon": "CardC",
        "IsSellOutShow": 1,
        "Tag": 1,
        "UiType": 2,
        "LogType": 2,
        "MutexPurchaseIdStr": 83028
    }
]