[
    {
        "Info": 30020309,
        "Key": "PB1",
        "X": 932,
        "Y": 649
    },
    {
        "Info": 30020309,
        "Key": "JX1",
        "X": 1405,
        "Y": 3331
    },
    {
        "Info": 30020309,
        "Key": "JX2",
        "X": 3430,
        "Y": 2062
    },
    {
        "Info": 30020309,
        "Key": "JX3",
        "X": 376,
        "Y": 1983
    },
    {
        "Info": 30020309,
        "Key": "JX4",
        "X": 2572,
        "Y": 539
    },
    {
        "Info": 30020309,
        "Key": "JX5",
        "X": 2251,
        "Y": 2386
    },
    {
        "Info": 30020309,
        "Key": "S1",
        "X": 1919,
        "Y": 1926
    },
    {
        "Info": 30020309,
        "Key": "B101",
        "X": 1666,
        "Y": 3396
    },
    {
        "Info": 30020309,
        "Key": "B102",
        "X": 1211,
        "Y": 3111
    },
    {
        "Info": 30020309,
        "Key": "B201",
        "X": 3374,
        "Y": 2279
    },
    {
        "Info": 30020309,
        "Key": "B202",
        "X": 3428,
        "Y": 1823
    },
    {
        "Info": 30020309,
        "Key": "B301",
        "X": 396,
        "Y": 1742
    },
    {
        "Info": 30020309,
        "Key": "B302",
        "X": 487,
        "Y": 2214
    },
    {
        "Info": 30020309,
        "Key": "B401",
        "X": 2384,
        "Y": 410
    },
    {
        "Info": 30020309,
        "Key": "B402",
        "X": 2760,
        "Y": 667
    },
    {
        "Info": 30130114,
        "Key": "PB1",
        "X": 2547,
        "Y": 3121
    },
    {
        "Info": 30130114,
        "Key": "S1",
        "X": 2298,
        "Y": 2756
    },
    {
        "Info": 30130114,
        "Key": "B101",
        "X": 1879,
        "Y": 2484
    },
    {
        "Info": 30130114,
        "Key": "B102",
        "X": 2158,
        "Y": 2313
    },
    {
        "Info": 30130114,
        "Key": "B103",
        "X": 1863,
        "Y": 2313
    },
    {
        "Info": 30130114,
        "Key": "B104",
        "X": 1995,
        "Y": 2243
    },
    {
        "Info": 30130114,
        "Key": "S2",
        "X": 2104,
        "Y": 2469
    },
    {
        "Info": 30130114,
        "Key": "B201",
        "X": 1451,
        "Y": 1823
    },
    {
        "Info": 30130114,
        "Key": "B202",
        "X": 1692,
        "Y": 1676
    }
]