[
    {
        "Id": 9000001,
        "Name": "Gray Raven",
        "ImgSrc": "Assets/Product/Texture/Image/RolePlayerSp/RolePlayer01.png",
        "LockDescId": 1,
        "ConvertItemId": 1,
        "ConvertItemCount": 10000,
        "Description": "Player Portrait",
        "WorldDesc": "One of the default portraits.",
        "Priority": 53
    },
    {
        "Id": 9000002,
        "Name": "Repairer",
        "ImgSrc": "Assets/Product/Texture/Image/RolePlayerSp/RolePlayer02.png",
        "LockDescId": 1,
        "ConvertItemId": 1,
        "ConvertItemCount": 10000,
        "Description": "Player Portrait",
        "WorldDesc": "One of the default portraits.",
        "Priority": 52
    },
    {
        "Id": 9000003,
        "Name": "Tag",
        "ImgSrc": "Assets/Product/Texture/Image/RolePlayerSp/RolePlayer03.png",
        "LockDescId": 1,
        "ConvertItemId": 1,
        "ConvertItemCount": 10000,
        "Description": "Player Portrait",
        "WorldDesc": "One of the default portraits.",
        "Priority": 50
    },
    {
        "Id": 9010101,
        "Name": "Portrait - Lotus",
        "ImgSrc": "Assets/Product/Texture/Image/RolePlayerSp/RoleHeadluxiya5.png",
        "LockDescId": 2,
        "ConvertItemId": 1,
        "ConvertItemCount": 10000,
        "Description": "Player Portrait",
        "WorldDesc": "The final developed form of Ultima Awakened Constructs after countless battles.",
        "Priority": 30
    },
    {
        "Id": 9010102,
        "Name": "Portrait - Dawn",
        "ImgSrc": "Assets/Product/Texture/Image/RolePlayerSp/RoleHeadluxiya5S.png",
        "LockDescId": 2,
        "ConvertItemId": 1,
        "ConvertItemCount": 10000,
        "Description": "Player Portrait",
        "WorldDesc": "The final developed form of Ultima Awakened Constructs after countless battles.",
        "Priority": 29
    },
    {
        "Id": 9010103,
        "Name": "Portrait - Crimson Abyss",
        "ImgSrc": "Assets/Product/Texture/Image/RolePlayerSp/RoleHeadluxiyaaerfa5SS.png",
        "LockDescId": 2,
        "ConvertItemId": 1,
        "ConvertItemCount": 10000,
        "Description": "Player Portrait",
        "WorldDesc": "The final developed form of Ultima Awakened Constructs after countless battles.",
        "Priority": 28
    },
    {
        "Id": 9010201,
        "Name": "Portrait - Eclipse",
        "ImgSrc": "Assets/Product/Texture/Image/RolePlayerSp/RoleHeadLifu5.png",
        "LockDescId": 2,
        "ConvertItemId": 1,
        "ConvertItemCount": 10000,
        "Description": "Player Portrait",
        "WorldDesc": "The final developed form of Ultima Awakened Constructs after countless battles.",
        "Priority": 27
    },
    {
        "Id": 9010202,
        "Name": "Portrait - Lux",
        "ImgSrc": "Assets/Product/Texture/Image/RolePlayerSp/RoleHeadLifu5S.png",
        "LockDescId": 2,
        "ConvertItemId": 1,
        "ConvertItemCount": 10000,
        "Description": "Player Portrait",
        "WorldDesc": "The final developed form of Ultima Awakened Constructs after countless battles.",
        "Priority": 26
    },
    {
        "Id": 9010203,
        "Name": "Portrait - Luminance",
        "ImgSrc": "Assets/Product/Texture/Image/RolePlayerSp/RoleHeadLifu5SS.png",
        "LockDescId": 2,
        "ConvertItemId": 1,
        "ConvertItemCount": 10000,
        "Description": "Player Portrait",
        "WorldDesc": "The final developed form of Ultima Awakened Constructs after countless battles.",
        "Priority": 25
    },
    {
        "Id": 9010301,
        "Name": "Portrait - Palefire",
        "ImgSrc": "Assets/Product/Texture/Image/RolePlayerSp/RoleHeadLi5.png",
        "LockDescId": 2,
        "ConvertItemId": 1,
        "ConvertItemCount": 10000,
        "Description": "Player Portrait",
        "WorldDesc": "The final developed form of Ultima Awakened Constructs after countless battles.",
        "Priority": 24
    },
    {
        "Id": 9010302,
        "Name": "Portrait - Entropy",
        "ImgSrc": "Assets/Product/Texture/Image/RolePlayerSp/RoleHeadLi5SS.png",
        "LockDescId": 2,
        "ConvertItemId": 1,
        "ConvertItemCount": 10000,
        "Description": "Player Portrait",
        "WorldDesc": "The final developed form of Ultima Awakened Constructs after countless battles.",
        "Priority": 23
    },
    {
        "Id": 9010401,
        "Name": "Portrait - Storm",
        "ImgSrc": "Assets/Product/Texture/Image/RolePlayerSp/RoleHeadYongyechao5.png",
        "LockDescId": 2,
        "ConvertItemId": 1,
        "ConvertItemCount": 10000,
        "Description": "Player Portrait",
        "WorldDesc": "The final developed form of Ultima Awakened Constructs after countless battles.",
        "Priority": 22
    },
    {
        "Id": 9010402,
        "Name": "Portrait - Pulse",
        "ImgSrc": "Assets/Product/Texture/Image/RolePlayerSp/RoleHeadYongyechao5SS.png",
        "LockDescId": 2,
        "ConvertItemId": 1,
        "ConvertItemCount": 10000,
        "Description": "Player Portrait",
        "WorldDesc": "The final developed form of Ultima Awakened Constructs after countless battles.",
        "Priority": 21
    },
    {
        "Id": 9010501,
        "Name": "Portrait - Blast",
        "ImgSrc": "Assets/Product/Texture/Image/RolePlayerSp/RoleHeadKalienina5.png",
        "LockDescId": 2,
        "ConvertItemId": 1,
        "ConvertItemCount": 10000,
        "Description": "Player Portrait",
        "WorldDesc": "The final developed form of Ultima Awakened Constructs after countless battles.",
        "Priority": 20
    },
    {
        "Id": 9010502,
        "Name": "Portrait - Ember",
        "ImgSrc": "Assets/Product/Texture/Image/RolePlayerSp/RoleHeadKalienina5SS.png",
        "LockDescId": 2,
        "ConvertItemId": 1,
        "ConvertItemCount": 10000,
        "Description": "Player Portrait",
        "WorldDesc": "The final developed form of Ultima Awakened Constructs after countless battles.",
        "Priority": 19
    },
    {
        "Id": 9010601,
        "Name": "Portrait - Nightblade",
        "ImgSrc": "Assets/Product/Texture/Image/RolePlayerSp/RoleHeadDubian5.png",
        "LockDescId": 2,
        "ConvertItemId": 1,
        "ConvertItemCount": 10000,
        "Description": "Player Portrait",
        "WorldDesc": "The final developed form of Ultima Awakened Constructs after countless battles.",
        "Priority": 18
    },
    {
        "Id": 9010602,
        "Name": "Portrait - Astral",
        "ImgSrc": "Assets/Product/Texture/Image/RolePlayerSp/RoleHeadDubian5SS.png",
        "LockDescId": 2,
        "ConvertItemId": 1,
        "ConvertItemCount": 10000,
        "Description": "Player Portrait",
        "WorldDesc": "The final developed form of Ultima Awakened Constructs after countless battles.",
        "Priority": 17
    },
    {
        "Id": 9010701,
        "Name": "Portrait - Zero",
        "ImgSrc": "Assets/Product/Texture/Image/RolePlayerSp/RoleHeadAolisuo5.png",
        "LockDescId": 2,
        "ConvertItemId": 1,
        "ConvertItemCount": 10000,
        "Description": "Player Portrait",
        "WorldDesc": "The final developed form of Ultima Awakened Constructs after countless battles.",
        "Priority": 16
    },
    {
        "Id": 9010801,
        "Name": "Portrait - Bastion",
        "ImgSrc": "Assets/Product/Texture/Image/RolePlayerSp/RoleHeadShenwei5.png",
        "LockDescId": 2,
        "ConvertItemId": 1,
        "ConvertItemCount": 10000,
        "Description": "Player Portrait",
        "WorldDesc": "The final developed form of Ultima Awakened Constructs after countless battles.",
        "Priority": 15
    },
    {
        "Id": 9010802,
        "Name": "Portrait - Tenebrion",
        "ImgSrc": "Assets/Product/Texture/Image/RolePlayerSp/RoleHeadShenwei5SS.png",
        "LockDescId": 2,
        "ConvertItemId": 1,
        "ConvertItemCount": 10000,
        "Description": "Player Portrait",
        "WorldDesc": "The final developed form of Ultima Awakened Constructs after countless battles.",
        "Priority": 14
    },
    {
        "Id": 9010901,
        "Name": "Portrait - Brilliance",
        "ImgSrc": "Assets/Product/Texture/Image/RolePlayerSp/RoleHeadAila5.png",
        "LockDescId": 2,
        "ConvertItemId": 1,
        "ConvertItemCount": 10000,
        "Description": "Player Portrait",
        "WorldDesc": "The final developed form of Ultima Awakened Constructs after countless battles.",
        "Priority": 13
    },
    {
        "Id": 9080001,
        "Name": "Portrait - Task Force",
        "ImgSrc": "Assets/Product/Texture/Image/RolePlayerSp/RolePlayer06.png",
        "LockDescId": 8,
        "ConvertItemId": 1,
        "ConvertItemCount": 10000,
        "Description": "Player Portrait",
        "WorldDesc": "The symbol of Task Force.",
        "Priority": 12
    },
    {
        "Id": 9090001,
        "Name": "Kuroro",
        "ImgSrc": "Assets/Product/Texture/Image/RolePlayerSp/RolePlayer04.png",
        "LockDescId": 100,
        "ConvertItemId": 1,
        "ConvertItemCount": 10000,
        "Description": "Player Portrait",
        "WorldDesc": "A mysterious mechanical race found in many places on the surface. Has a keen interest in collecting Cogs.",
        "Priority": 11
    },
    {
        "Id": 9090002,
        "Name": "Portrait - Special Identity",
        "ImgSrc": "Assets/Product/Texture/Image/RolePlayerSp/RolePlayer05.png",
        "LockDescId": 4,
        "ConvertItemId": 1,
        "ConvertItemCount": 10000,
        "Description": "Player Portrait",
        "WorldDesc": "Sorry, but I refuse to reveal my true identity as a commandant.",
        "Effect": "Assets/Product/Effect/Prefab/FxUi/FxUiComponent/FxUiTouxiang.prefab",
        "Priority": 10
    },
    {
        "Id": 9090005,
        "Name": "Mr. Potato",
        "ImgSrc": "Assets/Product/Texture/Image/RolePlayerSp/RolePlayer12.png",
        "LockDescId": 12,
        "ConvertItemId": 1,
        "ConvertItemCount": 10000,
        "Description": "Player Portrait",
        "WorldDesc": "A popular fast food dish in Babylonia. Still going strong after many challenges.",
        "Priority": 7
    },
    {
        "Id": 9090006,
        "Name": "RIP Potato",
        "ImgSrc": "Assets/Product/Texture/Image/RolePlayerSp/RolePlayer13.png",
        "LockDescId": 13,
        "ConvertItemId": 1,
        "ConvertItemCount": 10000,
        "Description": "Player Portrait",
        "WorldDesc": "In commemoration of Mr. Potato, now ripened and cooked.",
        "Priority": 6
    },
    {
        "Id": 9053002,
        "Name": "Portrait - Volatile Priestess",
        "ImgSrc": "Assets/Product/Texture/Image/RolePlayerSp/RoleHeadJpR3LuxiyaSS.png",
        "LockDescId": 101,
        "ConvertItemId": 1,
        "ConvertItemCount": 10000,
        "Description": "Player Portrait",
        "WorldDesc": "A portrait representing the ritual to worship wild gods in ancient times. Recreated from old data of the Earth.",
        "Priority": 3
    }
]