[
    {
        "Id": 95010001,
        "Name": "能量包",
        "Shape": 2,
        "SizeX": 2,
        "Speed": 8,
        "TargetType": 4,
        "LiveTime": 999,
        "DeadExplosion": 1,
        "HitCount": "-1",
        "HitEffect": [],
        "Effect": "FxDropPower",
        "DamageCount": "-1",
        "LineType": 3,
        "LineParams": [
            "-80",
            0.1,
            10,
            0,
            0,
            0,
            0
        ],
        "ScaleParams": [],
        "BornPosition": 3,
        "ChildDelay": 999,
        "ChildCountLimit": 1,
        "ChildId": 95010002,
        "BornChildWhileDead": 1,
        "BornDirectionType": 4,
        "BeHitCenter": 1,
        "Magic": [],
        "MagicLauncherNpc": [],
        "EffectHeight": 1,
        "HitOnJoint": "HitCase",
        "BindLauncher": 0,
        "ActiveDelayTime": 999,
        "ExplodeOnFloor": 1,
        "DodgeLimitMark": 0
    },
    {
        "Id": 95010002,
        "Name": "·····",
        "Shape": 2,
        "SizeX": 2,
        "Speed": 0,
        "TargetType": 4,
        "LiveTime": 999,
        "DeadExplosion": 1,
        "HitCount": 1,
        "HitEffect": [],
        "Effect": "FxDropPower",
        "DamageCount": 1,
        "ExplosionEffect": "FxDropPowerBeHit",
        "LineType": 1,
        "LineParams": [
            null,
            null,
            null,
            null,
            0,
            0,
            0
        ],
        "ScaleParams": [],
        "BornPosition": 2,
        "BornDirectionType": 2,
        "BeHitCenter": 1,
        "Magic": [
            950111
        ],
        "MagicLauncherNpc": [],
        "EffectHeight": 0,
        "HitOnJoint": "HitCase",
        "BindLauncher": 0,
        "DodgeLimitMark": 0
    },
    {
        "Id": 95010003,
        "Name": "速度包",
        "Shape": 2,
        "SizeX": 2,
        "Speed": 8,
        "TargetType": 4,
        "LiveTime": 999,
        "DeadExplosion": 1,
        "HitCount": "-1",
        "HitEffect": [],
        "Effect": "FxDropSpeed",
        "DamageCount": "-1",
        "LineType": 3,
        "LineParams": [
            "-80",
            0.1,
            10,
            0,
            0,
            0,
            0
        ],
        "ScaleParams": [],
        "BornPosition": 3,
        "ChildDelay": 999,
        "ChildCountLimit": 1,
        "ChildId": 95010004,
        "BornChildWhileDead": 1,
        "BornDirectionType": 4,
        "BeHitCenter": 1,
        "Magic": [],
        "MagicLauncherNpc": [],
        "EffectHeight": 1,
        "HitOnJoint": "HitCase",
        "BindLauncher": 0,
        "ActiveDelayTime": 999,
        "ExplodeOnFloor": 1,
        "DodgeLimitMark": 0
    },
    {
        "Id": 95010004,
        "Name": "·····",
        "Shape": 2,
        "SizeX": 2,
        "Speed": 0,
        "TargetType": 4,
        "LiveTime": 999,
        "DeadExplosion": 1,
        "HitCount": 1,
        "HitEffect": [],
        "Effect": "FxDropSpeed",
        "DamageCount": 1,
        "ExplosionEffect": "FxDropSpeedBeHit",
        "LineType": 1,
        "LineParams": [
            null,
            null,
            null,
            null,
            0,
            0,
            0
        ],
        "ScaleParams": [],
        "BornPosition": 2,
        "BornDirectionType": 2,
        "BeHitCenter": 1,
        "Magic": [
            950112
        ],
        "MagicLauncherNpc": [],
        "EffectHeight": 0,
        "HitOnJoint": "HitCase",
        "BindLauncher": 0,
        "DodgeLimitMark": 0
    },
    {
        "Id": 95010005,
        "Name": "生命值包",
        "Shape": 2,
        "SizeX": 2,
        "Speed": 8,
        "TargetType": 4,
        "LiveTime": 999,
        "DeadExplosion": 1,
        "HitCount": "-1",
        "HitEffect": [],
        "Effect": "FxDropCure",
        "DamageCount": "-1",
        "LineType": 3,
        "LineParams": [
            "-80",
            0.1,
            10,
            0,
            0,
            0,
            0
        ],
        "ScaleParams": [],
        "BornPosition": 3,
        "ChildDelay": 999,
        "ChildCountLimit": 1,
        "ChildId": 95010006,
        "BornChildWhileDead": 1,
        "BornDirectionType": 4,
        "BeHitCenter": 1,
        "Magic": [],
        "MagicLauncherNpc": [],
        "EffectHeight": 1,
        "HitOnJoint": "HitCase",
        "BindLauncher": 0,
        "ActiveDelayTime": 999,
        "ExplodeOnFloor": 1,
        "DodgeLimitMark": 0
    },
    {
        "Id": 95010006,
        "Name": "·····",
        "Shape": 2,
        "SizeX": 2,
        "Speed": 0,
        "TargetType": 4,
        "LiveTime": 999,
        "DeadExplosion": 1,
        "HitCount": 1,
        "HitEffect": [],
        "Effect": "FxDropCure",
        "DamageCount": 1,
        "ExplosionEffect": "FxDropCureBeHit",
        "LineType": 1,
        "LineParams": [
            null,
            null,
            null,
            null,
            0,
            0,
            0
        ],
        "ScaleParams": [],
        "BornPosition": 2,
        "BornDirectionType": 2,
        "BeHitCenter": 1,
        "Magic": [
            950113
        ],
        "MagicLauncherNpc": [],
        "EffectHeight": 0,
        "HitOnJoint": "HitCase",
        "BindLauncher": 0,
        "DodgeLimitMark": 0
    },
    {
        "Id": 95010021,
        "Name": "·····",
        "Shape": 2,
        "SizeX": 2,
        "Speed": 0,
        "TargetType": 4,
        "LiveTime": 999,
        "DeadExplosion": 1,
        "HitCount": 1,
        "HitEffect": [],
        "Effect": "FxDropCure",
        "DamageCount": 1,
        "ExplosionEffect": "FxDropCureBeHit",
        "LineType": 1,
        "LineParams": [
            null,
            null,
            null,
            null,
            0,
            0,
            0
        ],
        "ScaleParams": [],
        "BornPosition": 2,
        "BornDirectionType": 2,
        "BeHitCenter": 1,
        "Magic": [
            950113
        ],
        "MagicLauncherNpc": [],
        "EffectHeight": 0,
        "HitOnJoint": "HitCase",
        "BindLauncher": 0,
        "DodgeLimitMark": 0
    },
    {
        "Id": 95010031,
        "Name": "冲锋",
        "Shape": 1,
        "SizeX": 3,
        "SizeY": 7,
        "OffsetY": 2,
        "Speed": 0,
        "TargetType": 6,
        "LiveTime": 3,
        "HitCount": "-1",
        "RepeatDamage": 0,
        "HitEffect": [],
        "DamageInterval": 0.1,
        "Effect": "FxNpcYujing02",
        "DamageCount": "-1",
        "LineType": 1,
        "LineParams": [
            null,
            null,
            null,
            null,
            0,
            0,
            0
        ],
        "ScaleParams": [],
        "BornPosition": 0,
        "BornDirectionType": 0,
        "BeHitCenter": 1,
        "BeHitState": 950100311,
        "Magic": [
            950114,
            200003
        ],
        "MagicLauncherNpc": [
            816004,
            null,
            950109
        ],
        "EffectHeight": 0,
        "HitOnJoint": "HitCase",
        "ResizeEffect": 1,
        "BindLauncher": 1,
        "DodgeLimitMark": 0
    },
    {
        "Id": 95010041,
        "Name": "小坦克-Skill-01-炮击",
        "Shape": 2,
        "SizeX": 1,
        "Speed": 30,
        "TargetType": 6,
        "LiveTime": 5,
        "DeadExplosion": 1,
        "HitCount": 1,
        "HitEffect": [
            "FxDibingShouji"
        ],
        "StartJoint": "EffectCase1",
        "Effect": "FxMe1DestroyerMd001001Attack02Dandao",
        "DamageCount": 1,
        "LineType": 1,
        "LineParams": [
            null,
            null,
            null,
            null,
            0,
            0,
            0
        ],
        "ScaleParams": [],
        "BornPosition": 0,
        "ChildDelay": 9999,
        "ChildCountLimit": 1,
        "ChildId": 95010211,
        "BornChildWhileDead": 1,
        "BornDirectionType": 1,
        "BeHitCenter": 1,
        "Magic": [],
        "MagicLauncherNpc": [],
        "EffectHeight": 0,
        "HitOnJoint": "HitCase",
        "BindLauncher": 0,
        "DodgeLimitMark": 1
    },
    {
        "Id": 95010101,
        "Name": "小坦克-Skill-01-激光射线",
        "Shape": 1,
        "SizeX": 2,
        "SizeY": 20,
        "OffsetY": 10,
        "Speed": 0,
        "TargetType": 6,
        "LiveTime": 0.85,
        "HitCount": "-1",
        "RepeatDamage": 1,
        "HitEffect": [
            "FxDibingShouji"
        ],
        "DamageInterval": 0.1,
        "DamageCount": "-1",
        "LineType": 1,
        "LineParams": [
            null,
            null,
            null,
            null,
            0,
            0,
            0
        ],
        "ScaleParams": [],
        "BornPosition": 0,
        "BornDirectionType": 0,
        "BeHitCenter": 1,
        "BeHitState": 950101011,
        "Magic": [
            811003
        ],
        "MagicLauncherNpc": [
            816004,
            null,
            950109
        ],
        "EffectHeight": 0,
        "HitOnJoint": "HitCase",
        "ResizeEffect": 1,
        "BindLauncher": 0,
        "DodgeLimitMark": 1
    },
    {
        "Id": 95010201,
        "Name": "小坦克-Skill-01-炮击",
        "Shape": 2,
        "SizeX": 1,
        "OffsetY": 3,
        "Speed": 30,
        "TargetType": 6,
        "LiveTime": 5,
        "DeadExplosion": 1,
        "HitCount": 1,
        "HitEffect": [
            "FxDibingShouji"
        ],
        "StartJoint": "EffectCase1",
        "Effect": "FxMe1DestroyerMd001001Attack02Dandao",
        "DamageCount": 1,
        "LineType": 1,
        "LineParams": [
            null,
            null,
            null,
            null,
            0,
            0,
            0
        ],
        "ScaleParams": [],
        "BornPosition": 0,
        "ChildDelay": 9999,
        "ChildCountLimit": 1,
        "ChildId": 95010211,
        "BornChildWhileDead": 1,
        "BornDirectionType": 0,
        "BeHitCenter": 1,
        "Magic": [],
        "MagicLauncherNpc": [],
        "EffectHeight": 0,
        "HitOnJoint": "HitCase",
        "BindLauncher": 0,
        "DodgeLimitMark": 1
    },
    {
        "Id": 95010202,
        "Name": "小坦克-Skill-01-炮击",
        "Shape": 2,
        "SizeX": 1,
        "OffsetY": 3,
        "Speed": 30,
        "TargetType": 6,
        "LiveTime": 5,
        "DeadExplosion": 1,
        "HitCount": 1,
        "HitEffect": [
            "FxDibingShouji"
        ],
        "StartJoint": "EffectCase1",
        "Effect": "FxMe1DestroyerMd001001Attack02Dandao",
        "DamageCount": 1,
        "LineType": 1,
        "LineParams": [
            null,
            null,
            null,
            null,
            0,
            0,
            0
        ],
        "ScaleParams": [],
        "BornPosition": 0,
        "ChildDelay": 9999,
        "ChildCountLimit": 1,
        "ChildId": 95010211,
        "BornChildWhileDead": 1,
        "BornDirectionType": 0,
        "BeHitCenter": 1,
        "Magic": [],
        "MagicLauncherNpc": [],
        "EffectHeight": 0,
        "HitOnJoint": "HitCase",
        "BindLauncher": 0,
        "DodgeLimitMark": 1
    },
    {
        "Id": 95010203,
        "Name": "小坦克-Skill-01-炮击",
        "Shape": 2,
        "SizeX": 1,
        "OffsetY": 3,
        "Speed": 30,
        "TargetType": 6,
        "LiveTime": 5,
        "DeadExplosion": 1,
        "HitCount": 1,
        "HitEffect": [
            "FxDibingShouji"
        ],
        "StartJoint": "EffectCase1",
        "Effect": "FxMe1DestroyerMd001001Attack02Dandao",
        "DamageCount": 1,
        "LineType": 1,
        "LineParams": [
            null,
            null,
            null,
            null,
            0,
            0,
            0
        ],
        "ScaleParams": [],
        "BornPosition": 0,
        "ChildDelay": 9999,
        "ChildCountLimit": 1,
        "ChildId": 95010211,
        "BornChildWhileDead": 1,
        "BornDirectionType": 0,
        "BeHitCenter": 1,
        "Magic": [],
        "MagicLauncherNpc": [],
        "EffectHeight": 0,
        "HitOnJoint": "HitCase",
        "BindLauncher": 0,
        "DodgeLimitMark": 1
    },
    {
        "Id": 95010204,
        "Name": "小坦克-Skill-01-炮击",
        "Shape": 2,
        "SizeX": 1,
        "OffsetY": 3,
        "Speed": 30,
        "TargetType": 6,
        "LiveTime": 5,
        "DeadExplosion": 1,
        "HitCount": 1,
        "HitEffect": [
            "FxDibingShouji"
        ],
        "StartJoint": "EffectCase1",
        "Effect": "FxMe1DestroyerMd001001Attack02Dandao",
        "DamageCount": 1,
        "LineType": 1,
        "LineParams": [
            null,
            null,
            null,
            null,
            0,
            0,
            0
        ],
        "ScaleParams": [],
        "BornPosition": 0,
        "ChildDelay": 9999,
        "ChildCountLimit": 1,
        "ChildId": 95010211,
        "BornChildWhileDead": 1,
        "BornDirectionType": 0,
        "BeHitCenter": 1,
        "Magic": [],
        "MagicLauncherNpc": [],
        "EffectHeight": 0,
        "HitOnJoint": "HitCase",
        "BindLauncher": 0,
        "DodgeLimitMark": 1
    },
    {
        "Id": 95010205,
        "Name": "小坦克-Skill-01-炮击",
        "Shape": 2,
        "SizeX": 1,
        "OffsetY": 3,
        "Speed": 30,
        "TargetType": 6,
        "LiveTime": 5,
        "DeadExplosion": 1,
        "HitCount": 1,
        "HitEffect": [
            "FxDibingShouji"
        ],
        "StartJoint": "EffectCase1",
        "Effect": "FxMe1DestroyerMd001001Attack02Dandao",
        "DamageCount": 1,
        "LineType": 1,
        "LineParams": [
            null,
            null,
            null,
            null,
            0,
            0,
            0
        ],
        "ScaleParams": [],
        "BornPosition": 0,
        "ChildDelay": 9999,
        "ChildCountLimit": 1,
        "ChildId": 95010211,
        "BornChildWhileDead": 1,
        "BornDirectionType": 0,
        "BeHitCenter": 1,
        "Magic": [],
        "MagicLauncherNpc": [],
        "EffectHeight": 0,
        "HitOnJoint": "HitCase",
        "BindLauncher": 0,
        "DodgeLimitMark": 1
    },
    {
        "Id": 95010211,
        "Name": "小坦克-Skill-01-炮击",
        "Shape": 2,
        "SizeX": 2,
        "Speed": 0,
        "TargetType": 6,
        "LiveTime": 0.1,
        "HitCount": 1,
        "HitEffect": [],
        "DamageCount": 1,
        "LineType": 1,
        "LineParams": [
            null,
            null,
            null,
            null,
            0,
            0,
            0
        ],
        "ScaleParams": [],
        "BornPosition": 2,
        "ChildCountLimit": 1,
        "ChildId": 95010212,
        "BornDirectionType": 0,
        "BeHitCenter": 1,
        "Magic": [
            811005,
            200003
        ],
        "MagicLauncherNpc": [
            816004,
            null,
            950109
        ],
        "EffectHeight": 0,
        "HitOnJoint": "HitCase",
        "BindLauncher": 0,
        "DodgeLimitMark": 0
    },
    {
        "Id": 95010212,
        "Name": "小坦克-Skill-01-炮击",
        "Shape": 2,
        "SizeX": 2,
        "Speed": 0,
        "TargetType": 6,
        "LiveTime": 5,
        "HitCount": "-1",
        "HitEffect": [],
        "Effect": "FxMe1DestroyerMd001001Attack02Zha",
        "DamageCount": "-1",
        "LineType": 1,
        "LineParams": [
            null,
            null,
            null,
            null,
            0,
            0,
            0
        ],
        "ScaleParams": [],
        "BornPosition": 2,
        "BornDirectionType": 0,
        "BeHitCenter": 1,
        "Magic": [],
        "MagicLauncherNpc": [],
        "EffectHeight": 0,
        "HitOnJoint": "HitCase",
        "BindLauncher": 0,
        "DodgeLimitMark": 0
    },
    {
        "Id": 95010301,
        "Name": "小坦克-Skill-01-炮击",
        "Shape": 2,
        "SizeX": 3.5,
        "Speed": 0,
        "TargetType": 1,
        "LiveTime": 1.5,
        "HitCount": "-1",
        "RepeatDamage": 1,
        "HitEffect": [],
        "DamageInterval": 0.1,
        "DamageCount": "-1",
        "LineType": 1,
        "LineParams": [
            null,
            null,
            null,
            null,
            0,
            0,
            0
        ],
        "ScaleParams": [],
        "BornPosition": 0,
        "BornDirectionType": 0,
        "BeHitCenter": 1,
        "Magic": [
            100551
        ],
        "MagicLauncherNpc": [],
        "EffectHeight": 0,
        "HitOnJoint": "HitCase",
        "BindLauncher": 0,
        "DodgeLimitMark": 1
    },
    {
        "Id": 95010302,
        "Name": "小坦克-Skill-01-炮击",
        "Shape": 2,
        "SizeX": 3.5,
        "Speed": 0,
        "TargetType": 1,
        "LiveTime": 1.5,
        "HitCount": "-1",
        "RepeatDamage": 1,
        "HitEffect": [],
        "DamageInterval": 0.1,
        "DamageCount": "-1",
        "LineType": 1,
        "LineParams": [
            null,
            null,
            null,
            null,
            0,
            0,
            0
        ],
        "ScaleParams": [],
        "BornPosition": 0,
        "BornDirectionType": 0,
        "BeHitCenter": 1,
        "Magic": [],
        "MagicLauncherNpc": [],
        "EffectHeight": 0,
        "HitOnJoint": "HitCase",
        "BindLauncher": 0,
        "DodgeLimitMark": 1
    },
    {
        "Id": 95010401,
        "Name": "小坦克-Skill-01-炮击",
        "Shape": 2,
        "SizeX": 1,
        "OffsetY": 3,
        "Speed": 30,
        "TargetType": 6,
        "LiveTime": 5,
        "DeadExplosion": 1,
        "HitCount": 1,
        "HitEffect": [
            "FxDibingShouji"
        ],
        "StartJoint": "EffectCase1",
        "Effect": "FxMe1DestroyerMd001001Attack02Dandao",
        "DamageCount": 1,
        "LineType": 1,
        "LineParams": [
            null,
            null,
            null,
            null,
            0,
            0,
            0
        ],
        "ScaleParams": [],
        "BornPosition": 0,
        "ChildDelay": 9999,
        "ChildCountLimit": 1,
        "ChildId": 95010411,
        "BornChildWhileDead": 1,
        "BornDirectionType": 0,
        "BeHitCenter": 1,
        "Magic": [],
        "MagicLauncherNpc": [],
        "EffectHeight": 0,
        "HitOnJoint": "HitCase",
        "BindLauncher": 0,
        "DodgeLimitMark": 1
    },
    {
        "Id": 95010411,
        "Name": "小坦克-Skill-01-炮击",
        "Shape": 2,
        "SizeX": 2,
        "Speed": 0,
        "TargetType": 6,
        "LiveTime": 0.1,
        "HitCount": 1,
        "HitEffect": [],
        "DamageCount": 1,
        "LineType": 1,
        "LineParams": [
            null,
            null,
            null,
            null,
            0,
            0,
            0
        ],
        "ScaleParams": [],
        "BornPosition": 2,
        "ChildCountLimit": 1,
        "ChildId": 95010412,
        "BornDirectionType": 0,
        "BeHitCenter": 1,
        "Magic": [
            811005,
            200003
        ],
        "MagicLauncherNpc": [
            816004,
            null,
            950109
        ],
        "EffectHeight": 0,
        "HitOnJoint": "HitCase",
        "BindLauncher": 0,
        "DodgeLimitMark": 0
    },
    {
        "Id": 95010412,
        "Name": "小坦克-Skill-01-炮击",
        "Shape": 2,
        "SizeX": 2,
        "Speed": 0,
        "TargetType": 6,
        "LiveTime": 5,
        "HitCount": "-1",
        "HitEffect": [],
        "Effect": "FxMe1DestroyerMd001001Attack02Zha",
        "DamageCount": "-1",
        "LineType": 1,
        "LineParams": [
            null,
            null,
            null,
            null,
            0,
            0,
            0
        ],
        "ScaleParams": [],
        "BornPosition": 2,
        "BornDirectionType": 0,
        "BeHitCenter": 1,
        "Magic": [],
        "MagicLauncherNpc": [],
        "EffectHeight": 0,
        "HitOnJoint": "HitCase",
        "BindLauncher": 0,
        "DodgeLimitMark": 0
    },
    {
        "Id": 83300101,
        "Name": "抓取",
        "Shape": 0,
        "SizeX": 0.1,
        "OffsetX": "-2",
        "OffsetY": 5,
        "Speed": 0,
        "Direction": 90,
        "TargetType": 2,
        "LiveTime": 2,
        "HitCount": "-1",
        "HitEffect": [],
        "Effect": "FxMb1XiuMd010001Attack08",
        "DamageCount": "-1",
        "LineType": 1,
        "LineParams": [
            null,
            null,
            null,
            null,
            0,
            0,
            0
        ],
        "ScaleParams": [],
        "BornPosition": 0,
        "ChildDelay": 0.45,
        "ChildCountLimit": 1,
        "ChildId": 83300110,
        "BornDirectionType": 0,
        "BeHitCenter": 1,
        "Magic": [],
        "MagicLauncherNpc": [],
        "EffectHeight": 0,
        "HitOnJoint": "HitCase",
        "BindLauncher": 1,
        "DodgeLimitMark": 0
    },
    {
        "Id": 83300102,
        "Name": "抓取",
        "Shape": 0,
        "SizeX": 0.1,
        "OffsetX": 2,
        "OffsetY": 5,
        "Speed": 0,
        "Direction": "-90",
        "TargetType": 2,
        "LiveTime": 2,
        "HitCount": "-1",
        "HitEffect": [],
        "Effect": "FxMb1XiuMd010001Attack08",
        "DamageCount": "-1",
        "LineType": 1,
        "LineParams": [
            null,
            null,
            null,
            null,
            0,
            0,
            0
        ],
        "ScaleParams": [],
        "BornPosition": 0,
        "ChildDelay": 0.45,
        "ChildCountLimit": 1,
        "ChildId": 83300110,
        "BornDirectionType": 0,
        "BeHitCenter": 1,
        "Magic": [],
        "MagicLauncherNpc": [],
        "EffectHeight": 0,
        "HitOnJoint": "HitCase",
        "BindLauncher": 1,
        "DodgeLimitMark": 0
    },
    {
        "Id": 83300110,
        "Name": "抓取",
        "Shape": 1,
        "SizeX": 3.4,
        "SizeY": 7,
        "OffsetY": "-1",
        "Speed": 0,
        "TargetType": 2,
        "LiveTime": 0.1,
        "HitCount": "-1",
        "HitEffect": [],
        "DamageCount": "-1",
        "LineType": 1,
        "LineParams": [
            null,
            null,
            null,
            null,
            0,
            0,
            0
        ],
        "ScaleParams": [],
        "BornPosition": 2,
        "BornDirectionType": 2,
        "BeHitCenter": 1,
        "BeHitState": 833001101,
        "Magic": [
            811010,
            816004
        ],
        "MagicLauncherNpc": [
            831012
        ],
        "EffectHeight": 0,
        "HitOnJoint": "HitCase",
        "ResizeEffect": 1,
        "BindLauncher": 0,
        "DodgeLimitMark": 1
    },
    {
        "Id": 83300001,
        "Name": "下车被击退",
        "Shape": 2,
        "SizeX": 2,
        "OffsetY": 1,
        "Speed": 0,
        "TargetType": 3,
        "LiveTime": 0.1,
        "HitCount": 2,
        "HitEffect": [],
        "Effect": "FxNpcYujing01",
        "DamageCount": 2,
        "LineType": 1,
        "LineParams": [
            null,
            null,
            null,
            null,
            0,
            0,
            0
        ],
        "ScaleParams": [],
        "BornPosition": 0,
        "BornDirectionType": 0,
        "BeHitCenter": 2,
        "BeHitState": 833000011,
        "Magic": [],
        "MagicLauncherNpc": [],
        "EffectHeight": 0,
        "HitOnJoint": "HitCase",
        "ResizeEffect": 1,
        "BindLauncher": 0,
        "DodgeLimitMark": 0
    }
]